{
  "fetchedAt": "2026-06-27T19:50:15.173280+00:00",
  "state": {
    "slug": "oregon",
    "name": "Oregon"
  },
  "city": {
    "slug": "central-point",
    "name": "Central Point",
    "label": "Central Point, OR"
  },
  "source": "https://www.findpawpal.com/animal-shelter/oregon/central-point/",
  "offices": [
    {
      "officeId": 659532,
      "slug": "dogs-for-the-deaf-inc-659532",
      "name": "Dog's For the Deaf Inc",
      "address": "10175 Wheeler Road, Central Point, OR 97502",
      "phone": "541-826-9220",
      "image": "./img/shelter/office/659532.webp",
      "url": "https://www.findpawpal.com/animal-shelter/dogs-for-the-deaf-inc-659532/",
      "imageUrl": "https://cdn.findpawpal.com/office/659532.jpg?f=webp&w=730"
    }
  ]
}