{
  "officeId": 513008,
  "slug": "action-for-animals-513008",
  "name": "Action for Animals",
  "address": "PO Box 111, Metropolis, IL 62960",
  "street": "PO Box 111",
  "addressCity": "Metropolis",
  "stateCode": "IL",
  "zip": "62960",
  "phone": "618-524-4259",
  "image": "https://cdn.findpawpal.com/office/513008.jpg?f=webp&w=730",
  "url": "https://www.findpawpal.com/animal-shelter/action-for-animals-513008/",
  "stateSlug": "illinois",
  "stateName": "Illinois",
  "citySlug": "metropolis",
  "cityName": "Metropolis",
  "cityLabel": "Metropolis, IL",
  "sourceCityUrl": "https://www.findpawpal.com/animal-shelter/illinois/metropolis/",
  "fetchedAt": "2026-06-27T18:46:46.650818+00:00"
}