{
  "officeId": 580466,
  "slug": "animal-foundation-580466",
  "name": "Animal Foundation",
  "address": "621 River Avenue, Eugene, OR 97404",
  "street": "621 River Avenue",
  "addressCity": "Eugene",
  "stateCode": "OR",
  "zip": "97404",
  "phone": "541-689-9394",
  "image": "https://cdn.findpawpal.com/office/580466.jpg?f=webp&w=730",
  "url": "https://www.findpawpal.com/animal-shelter/animal-foundation-580466/",
  "stateSlug": "oregon",
  "stateName": "Oregon",
  "citySlug": "eugene",
  "cityName": "Eugene",
  "cityLabel": "Eugene, OR",
  "sourceCityUrl": "https://www.findpawpal.com/animal-shelter/oregon/eugene/",
  "fetchedAt": "2026-06-27T19:50:27.086671+00:00"
}