{
  "officeId": 633210,
  "slug": "austin-siamese-rescue-inc-633210",
  "name": "Austin Siamese Rescue, Inc.",
  "address": "PO Box 13474, Austin, TX 78711",
  "street": "PO Box 13474",
  "addressCity": "Austin",
  "stateCode": "TX",
  "zip": "78711",
  "phone": "512-261-6395",
  "image": "./img/shelter/office/633210.webp",
  "url": "https://www.findpawpal.com/animal-shelter/austin-siamese-rescue-inc-633210/",
  "stateSlug": "texas",
  "stateName": "Texas",
  "citySlug": "austin",
  "cityName": "Austin",
  "cityLabel": "Austin, TX",
  "sourceCityUrl": "https://www.findpawpal.com/animal-shelter/texas/austin/",
  "fetchedAt": "2026-06-27T20:02:47.288314+00:00",
  "imageUrl": "https://cdn.findpawpal.com/office/633210.jpg?f=webp&w=730"
}