{
  "officeId": 356308,
  "slug": "buhl-animal-shelter-356308",
  "name": "Buhl Animal Shelter",
  "address": "201 11th Avenue North, Buhl, ID 83316",
  "street": "201 11th Avenue North",
  "addressCity": "Buhl",
  "stateCode": "ID",
  "zip": "83316",
  "phone": "208-543-4326",
  "image": "./img/shelter/office/356308.webp",
  "url": "https://www.findpawpal.com/animal-shelter/buhl-animal-shelter-356308/",
  "stateSlug": "idaho",
  "stateName": "Idaho",
  "citySlug": "buhl",
  "cityName": "Buhl",
  "cityLabel": "Buhl, ID",
  "sourceCityUrl": "https://www.findpawpal.com/animal-shelter/idaho/buhl/",
  "fetchedAt": "2026-06-27T18:42:44.850920+00:00",
  "imageUrl": "https://cdn.findpawpal.com/office/356308.jpg?f=webp&w=730"
}