{
  "officeId": 588468,
  "slug": "creatures-comfort-animal-shelter-588468",
  "name": "Creatures Comfort Animal Shelter",
  "address": "116 West Walnut Street, Cardington, OH 43315",
  "street": "116 West Walnut Street",
  "addressCity": "Cardington",
  "stateCode": "OH",
  "zip": "43315",
  "phone": "419-864-2965",
  "image": "./img/shelter/office/588468.webp",
  "url": "https://www.findpawpal.com/animal-shelter/creatures-comfort-animal-shelter-588468/",
  "stateSlug": "ohio",
  "stateName": "Ohio",
  "citySlug": "cardington",
  "cityName": "Cardington",
  "cityLabel": "Cardington, OH",
  "sourceCityUrl": "https://www.findpawpal.com/animal-shelter/ohio/cardington/",
  "fetchedAt": "2026-06-27T19:43:31.040005+00:00",
  "imageUrl": "https://cdn.findpawpal.com/office/588468.jpg?f=webp&w=730"
}