{
  "officeId": 323074,
  "slug": "el-dorado-animal-control-323074",
  "name": "El Dorado Animal Control",
  "address": "204 North West Avenue, El Dorado, AR 71730",
  "street": "204 North West Avenue",
  "addressCity": "El Dorado",
  "stateCode": "AR",
  "zip": "71730",
  "phone": "870-881-4162",
  "image": "./img/shelter/office/323074.webp",
  "url": "https://www.findpawpal.com/animal-shelter/el-dorado-animal-control-323074/",
  "stateSlug": "arkansas",
  "stateName": "Arkansas",
  "citySlug": "el-dorado",
  "cityName": "El Dorado",
  "cityLabel": "El Dorado, AR",
  "sourceCityUrl": "https://www.findpawpal.com/animal-shelter/arkansas/el-dorado/",
  "fetchedAt": "2026-06-27T18:21:58.365209+00:00",
  "imageUrl": "https://cdn.findpawpal.com/office/323074.jpg?f=webp&w=730"
}