{
  "officeId": 451907,
  "slug": "erwin-dog-pound-451907",
  "name": "Erwin Dog Pound",
  "address": "PO Box 59, Erwin, TN 37650",
  "street": "PO Box 59",
  "addressCity": "Erwin",
  "stateCode": "TN",
  "zip": "37650",
  "phone": "615-743-6231",
  "image": "https://cdn.findpawpal.com/office/451907.jpg?f=webp&w=730",
  "url": "https://www.findpawpal.com/animal-shelter/erwin-dog-pound-451907/",
  "stateSlug": "tennessee",
  "stateName": "Tennessee",
  "citySlug": "erwin",
  "cityName": "Erwin",
  "cityLabel": "Erwin, TN",
  "sourceCityUrl": "https://www.findpawpal.com/animal-shelter/tennessee/erwin/",
  "fetchedAt": "2026-06-27T20:00:04.515483+00:00"
}