{
  "officeId": 356038,
  "slug": "hopes-haven-animal-shelter-356038",
  "name": "Hopes Haven Animal Shelter",
  "address": "53 Robinson Lane, St. Maries, ID 83861",
  "street": "53 Robinson Lane",
  "addressCity": "St. Maries",
  "stateCode": "ID",
  "zip": "83861",
  "phone": "208-245-7387",
  "image": "./img/shelter/office/356038.webp",
  "url": "https://www.findpawpal.com/animal-shelter/hopes-haven-animal-shelter-356038/",
  "stateSlug": "idaho",
  "stateName": "Idaho",
  "citySlug": "st-maries",
  "cityName": "St. Maries",
  "cityLabel": "St. Maries, ID",
  "sourceCityUrl": "https://www.findpawpal.com/animal-shelter/idaho/st-maries/",
  "fetchedAt": "2026-06-27T18:43:46.803056+00:00",
  "imageUrl": "https://cdn.findpawpal.com/office/356038.jpg?f=webp&w=730"
}