{
  "officeId": 622595,
  "slug": "lewis-upshur-animal-control-facility-622595",
  "name": "Lewis-Upshur Animal Control Facility",
  "address": "318 Mud Lick Road, Buckhannon, WV 26201",
  "street": "318 Mud Lick Road",
  "addressCity": "Buckhannon",
  "stateCode": "WV",
  "zip": "26201",
  "phone": "304-472-3865",
  "image": "https://cdn.findpawpal.com/office/622595.jpg?f=webp&w=730",
  "url": "https://www.findpawpal.com/animal-shelter/lewis-upshur-animal-control-facility-622595/",
  "stateSlug": "west-virginia",
  "stateName": "West Virginia",
  "citySlug": "buckhannon",
  "cityName": "Buckhannon",
  "cityLabel": "Buckhannon, WV",
  "sourceCityUrl": "https://www.findpawpal.com/animal-shelter/west-virginia/buckhannon/",
  "fetchedAt": "2026-06-27T20:19:59.521403+00:00"
}