{
  "officeId": 443709,
  "slug": "ohio-maltese-rescue-443709",
  "name": "Ohio Maltese Rescue",
  "address": "PO Box 223, Springfield, OH 45501",
  "street": "PO Box 223",
  "addressCity": "Springfield",
  "stateCode": "OH",
  "zip": "45501",
  "phone": "",
  "image": "https://cdn.findpawpal.com/office/443709.jpg?f=webp&w=730",
  "url": "https://www.findpawpal.com/animal-shelter/ohio-maltese-rescue-443709/",
  "stateSlug": "ohio",
  "stateName": "Ohio",
  "citySlug": "springfield",
  "cityName": "Springfield",
  "cityLabel": "Springfield, OH",
  "sourceCityUrl": "https://www.findpawpal.com/animal-shelter/ohio/springfield/",
  "fetchedAt": "2026-06-27T19:46:59.480052+00:00"
}