{
  "officeId": 227832,
  "slug": "pender-county-humane-society-227832",
  "name": "Pender County Humane Society",
  "address": "1407 Highway 53, Burgaw, NC 28425",
  "street": "1407 Highway 53",
  "addressCity": "Burgaw",
  "stateCode": "NC",
  "zip": "28425",
  "phone": "910-259-7022",
  "image": "./img/shelter/office/227832.webp",
  "url": "https://www.findpawpal.com/animal-shelter/pender-county-humane-society-227832/",
  "stateSlug": "north-carolina",
  "stateName": "North Carolina",
  "citySlug": "burgaw",
  "cityName": "Burgaw",
  "cityLabel": "Burgaw, NC",
  "sourceCityUrl": "https://www.findpawpal.com/animal-shelter/north-carolina/burgaw/",
  "fetchedAt": "2026-06-27T19:38:19.218718+00:00",
  "imageUrl": "https://cdn.findpawpal.com/office/227832.jpg?f=webp&w=730"
}