{
  "officeId": 363360,
  "slug": "pet-orphans-of-southern-california-363360",
  "name": "Pet Orphans of Southern California",
  "address": "7720 Gloria Avenue, Los Angeles, CA 91406",
  "street": "7720 Gloria Avenue",
  "addressCity": "Los Angeles",
  "stateCode": "CA",
  "zip": "91406",
  "phone": "818-901-0190",
  "image": "./img/shelter/office/363360.webp",
  "url": "https://www.findpawpal.com/animal-shelter/pet-orphans-of-southern-california-363360/",
  "stateSlug": "california",
  "stateName": "California",
  "citySlug": "los-angeles",
  "cityName": "Los Angeles",
  "cityLabel": "Los Angeles, CA",
  "sourceCityUrl": "https://www.findpawpal.com/animal-shelter/california/los-angeles/",
  "fetchedAt": "2026-06-27T18:27:28.259888+00:00",
  "imageUrl": "https://cdn.findpawpal.com/office/363360.jpg?f=webp&w=730"
}