{
  "officeId": 41191,
  "slug": "san-luis-valley-animal-welfare-society-41191",
  "name": "San Luis Valley Animal Welfare Society",
  "address": "PO Box 712, Alamosa, CO 81101",
  "street": "PO Box 712",
  "addressCity": "Alamosa",
  "stateCode": "CO",
  "zip": "81101",
  "phone": "719-587-9663",
  "image": "https://cdn.findpawpal.com/office/41191.jpg?f=webp&w=730",
  "url": "https://www.findpawpal.com/animal-shelter/san-luis-valley-animal-welfare-society-41191/",
  "stateSlug": "colorado",
  "stateName": "Colorado",
  "citySlug": "alamosa",
  "cityName": "Alamosa",
  "cityLabel": "Alamosa, CO",
  "sourceCityUrl": "https://www.findpawpal.com/animal-shelter/colorado/alamosa/",
  "fetchedAt": "2026-06-27T18:32:38.260308+00:00"
}