{
  "officeId": 561820,
  "slug": "shenandoah-county-animal-shelter-561820",
  "name": "Shenandoah County Animal Shelter",
  "address": "268 Landfill Road, Edinburg, VA 22824",
  "street": "268 Landfill Road",
  "addressCity": "Edinburg",
  "stateCode": "VA",
  "zip": "22824",
  "phone": "540-984-8955",
  "image": "./img/shelter/office/561820.webp",
  "url": "https://www.findpawpal.com/animal-shelter/shenandoah-county-animal-shelter-561820/",
  "stateSlug": "virginia",
  "stateName": "Virginia",
  "citySlug": "edinburg",
  "cityName": "Edinburg",
  "cityLabel": "Edinburg, VA",
  "sourceCityUrl": "https://www.findpawpal.com/animal-shelter/virginia/edinburg/",
  "fetchedAt": "2026-06-27T20:13:48.695985+00:00",
  "imageUrl": "https://cdn.findpawpal.com/office/561820.jpg?f=webp&w=730"
}