{
  "fetchedAt": "2026-06-27T19:40:15.499646+00:00",
  "state": {
    "slug": "north-carolina",
    "name": "North Carolina"
  },
  "city": {
    "slug": "maple",
    "name": "Maple",
    "label": "Maple, NC"
  },
  "source": "https://www.findpawpal.com/animal-shelter/north-carolina/maple/",
  "offices": [
    {
      "officeId": 226437,
      "slug": "currituck-humane-society-226437",
      "name": "Currituck Humane Society",
      "address": "204 Airport Rd, Maple, NC 27956",
      "phone": "252-453-6807",
      "image": "https://cdn.findpawpal.com/office/226437.jpg?f=webp&w=730",
      "url": "https://www.findpawpal.com/animal-shelter/currituck-humane-society-226437/"
    }
  ]
}