{
  "fetchedAt": "2026-06-27T19:41:10.497132+00:00",
  "state": {
    "slug": "north-carolina",
    "name": "North Carolina"
  },
  "city": {
    "slug": "rutherfordton",
    "name": "Rutherfordton",
    "label": "Rutherfordton, NC"
  },
  "source": "https://www.findpawpal.com/animal-shelter/north-carolina/rutherfordton/",
  "offices": [
    {
      "officeId": 231486,
      "slug": "rutherford-county-animal-control-231486",
      "name": "Rutherford County Animal Control",
      "address": "578 Laurel Hill Drive, Rutherfordton, NC 28139",
      "phone": "828-287-7738",
      "image": "./img/shelter/office/231486.webp",
      "url": "https://www.findpawpal.com/animal-shelter/rutherford-county-animal-control-231486/",
      "imageUrl": "https://cdn.findpawpal.com/office/231486.jpg?f=webp&w=730"
    },
    {
      "officeId": 239891,
      "slug": "rutherford-county-humane-society-239891",
      "name": "Rutherford County Humane Society",
      "address": "167 Pinkwood Drive, Rutherfordton, NC 28139",
      "phone": "828-286-0222",
      "image": "./img/shelter/office/239891.webp",
      "url": "https://www.findpawpal.com/animal-shelter/rutherford-county-humane-society-239891/",
      "imageUrl": "https://cdn.findpawpal.com/office/239891.jpg?f=webp&w=730"
    },
    {
      "officeId": 239935,
      "slug": "rutherford-county-animal-shelter-239935",
      "name": "Rutherford County Animal Shelter",
      "address": "198 North Washington Street, Rutherfordton, NC 28139",
      "phone": "",
      "image": "./img/shelter/office/239935.webp",
      "url": "https://www.findpawpal.com/animal-shelter/rutherford-county-animal-shelter-239935/",
      "imageUrl": "https://cdn.findpawpal.com/office/239935.jpg?f=webp&w=730"
    }
  ]
}