{
  "fetchedAt": "2026-06-27T19:20:25.331687+00:00",
  "state": {
    "slug": "missouri",
    "name": "Missouri"
  },
  "city": {
    "slug": "rolla",
    "name": "Rolla",
    "label": "Rolla, MO"
  },
  "source": "https://www.findpawpal.com/animal-shelter/missouri/rolla/",
  "offices": [
    {
      "officeId": 208152,
      "slug": "rolla-animal-shelter-208152",
      "name": "Rolla Animal Shelter",
      "address": "1915 Sharp Rd, Rolla, MO 65401",
      "phone": "573-364-6995",
      "image": "./img/shelter/office/208152.webp",
      "url": "https://www.findpawpal.com/animal-shelter/rolla-animal-shelter-208152/",
      "imageUrl": "https://cdn.findpawpal.com/office/208152.jpg?f=webp&w=730"
    },
    {
      "officeId": 241623,
      "slug": "phelps-county-animal-control-241623",
      "name": "Phelps County Animal Control",
      "address": "1304 Highway, Rolla, MO 65401",
      "phone": "573-426-4043",
      "image": "./img/shelter/office/241623.webp",
      "url": "https://www.findpawpal.com/animal-shelter/phelps-county-animal-control-241623/",
      "imageUrl": "https://cdn.findpawpal.com/office/241623.jpg?f=webp&w=730"
    }
  ]
}