{
  "fetchedAt": "2026-06-27T19:27:54.876841+00:00",
  "state": {
    "slug": "new-jersey",
    "name": "New Jersey"
  },
  "city": {
    "slug": "ocean",
    "name": "Ocean",
    "label": "Ocean, NJ"
  },
  "source": "https://www.findpawpal.com/animal-shelter/new-jersey/ocean/",
  "offices": [
    {
      "officeId": 94655,
      "slug": "humane-society-of-ocean-city-94655",
      "name": "Humane Society of Ocean City",
      "address": "PO Box 1254, Ocean, NJ 08226",
      "phone": "609-399-2018",
      "image": "https://cdn.findpawpal.com/office/94655.jpg?f=webp&w=730",
      "url": "https://www.findpawpal.com/animal-shelter/humane-society-of-ocean-city-94655/"
    }
  ]
}