{
  "fetchedAt": "2026-06-27T19:52:52.763748+00:00",
  "state": {
    "slug": "pennsylvania",
    "name": "Pennsylvania"
  },
  "city": {
    "slug": "emporium",
    "name": "Emporium",
    "label": "Emporium, PA"
  },
  "source": "https://www.findpawpal.com/animal-shelter/pennsylvania/emporium/",
  "offices": [
    {
      "officeId": 437368,
      "slug": "cameron-county-spca-437368",
      "name": "Cameron County SPCA",
      "address": "PO Box 132, Emporium, PA 15834",
      "phone": "814-486-0101",
      "image": "https://cdn.findpawpal.com/office/437368.jpg?f=webp&w=730",
      "url": "https://www.findpawpal.com/animal-shelter/cameron-county-spca-437368/"
    }
  ]
}