{
  "fetchedAt": "2026-06-27T18:51:04.919277+00:00",
  "state": {
    "slug": "indiana",
    "name": "Indiana"
  },
  "city": {
    "slug": "monrovia",
    "name": "Monrovia",
    "label": "Monrovia, IN"
  },
  "source": "https://www.findpawpal.com/animal-shelter/indiana/monrovia/",
  "offices": [
    {
      "officeId": 200642,
      "slug": "pak-rescue-200642",
      "name": "Pak Rescue",
      "address": "4038 West Briarwood Road, Monrovia, IN 46157",
      "phone": "317-460-2747",
      "image": "https://cdn.findpawpal.com/office/200642.jpg?f=webp&w=730",
      "url": "https://www.findpawpal.com/animal-shelter/pak-rescue-200642/"
    }
  ]
}