{
  "stateSlug": "virginia",
  "count": 320,
  "shelters": [
    {
      "slug": "best-little-cat-house-in-va-554817",
      "name": "Best Little Cat House In Va",
      "address": "26474 Honey Locust Road, Abingdon, VA 24211",
      "phone": "540-842-2404",
      "image": "https://cdn.findpawpal.com/office/554817.jpg?f=webp&w=730"
    },
    {
      "slug": "washington-county-va-cc-porter-animal-shelter-644703",
      "name": "Washington County VA CC Porter Animal Shelter",
      "address": "27252 Porter Lane, Abingdon, VA 24211",
      "phone": "540-676-6210",
      "image": "https://cdn.findpawpal.com/office/644703.jpg?f=webp&w=730"
    },
    {
      "slug": "accomack-county-animal-control-560846",
      "name": "Accomack County Animal Control",
      "address": "PO Box 149, Accomac, VA 23301",
      "phone": "757-787-1131",
      "image": "https://cdn.findpawpal.com/office/560846.jpg?f=webp&w=730"
    },
    {
      "slug": "aldie-animal-shelter-575563",
      "name": "Aldie Animal Shelter",
      "address": "39703 Goodpuppy Lane, Aldie, VA 20105",
      "phone": "703-957-4085",
      "image": "https://cdn.findpawpal.com/office/575563.jpg?f=webp&w=730"
    },
    {
      "slug": "friends-of-homeless-animals-579619",
      "name": "Friends Of Homeless Animals",
      "address": "39710 Goodpuppy Lane, Aldie, VA 20105",
      "phone": "703-385-0224",
      "image": "https://cdn.findpawpal.com/office/579619.jpg?f=webp&w=730"
    },
    {
      "slug": "animal-welfare-league-of-alexandria-683168",
      "name": "Animal Welfare League of Alexandria",
      "address": "4101 Eisenhower Ave, Alexandria, VA 22304",
      "phone": "703-838-4774",
      "image": "https://cdn.findpawpal.com/office/683168.jpg?f=webp&w=730"
    },
    {
      "slug": "cat-haven-575427",
      "name": "Cat Haven",
      "address": "6001 Beech Tree Drive, Alexandria, VA 22310",
      "phone": "703-960-3935",
      "image": "https://cdn.findpawpal.com/office/575427.jpg?f=webp&w=730"
    },
    {
      "slug": "kitten-orange-white-512161",
      "name": "Kitten Orange White",
      "address": "423 East Bellefonte Avenue, Alexandria, VA 22301",
      "phone": "",
      "image": "https://cdn.findpawpal.com/office/512161.jpg?f=webp&w=730"
    },
    {
      "slug": "operation-paws-for-homes-644510",
      "name": "Operation PAWS for Homes",
      "address": "PO Box 90813, Alexandria, VA 22309",
      "phone": "",
      "image": "https://cdn.findpawpal.com/office/644510.jpg?f=webp&w=730"
    },
    {
      "slug": "tails-high-inc-562089",
      "name": "Tails High, Inc.",
      "address": "1299A Quaker Hill Dr, Alexandria, VA 22314",
      "phone": "703-819-5240",
      "image": "https://cdn.findpawpal.com/office/562089.jpg?f=webp&w=730"
    },
    {
      "slug": "amelia-county-animal-control-644843",
      "name": "Amelia County Animal Control",
      "address": "16565 5 Forks Road, Amelia Court House, VA 23002",
      "phone": "804-561-3878",
      "image": "https://cdn.findpawpal.com/office/644843.jpg?f=webp&w=730"
    },
    {
      "slug": "amelia-patrons-for-animal-welfare-inc-529690",
      "name": "Amelia Patrons for Animal Welfare, Inc.",
      "address": "PO Box 725, Amelia Court House, VA 23002",
      "phone": "804-561-2244",
      "image": "https://cdn.findpawpal.com/office/529690.jpg?f=webp&w=730"
    },
    {
      "slug": "amherst-county-animal-control-706823",
      "name": "Amherst County Animal Control",
      "address": "PO Box 390, Amherst, VA 24521",
      "phone": "434-946-9400",
      "image": "https://cdn.findpawpal.com/office/706823.jpg?f=webp&w=730"
    },
    {
      "slug": "amherst-county-humane-society-683177",
      "name": "Amherst County Humane Society",
      "address": "322 Shelter Lane, Amherst, VA 24521",
      "phone": "804-946-9410",
      "image": "https://cdn.findpawpal.com/office/683177.jpg?f=webp&w=730"
    },
    {
      "slug": "humane-society-of-amherst-county-706824",
      "name": "Humane Society of Amherst County",
      "address": "318 Shelter Lane, Amherst, VA 24521",
      "phone": "434-946-2340",
      "image": "https://cdn.findpawpal.com/office/706824.jpg?f=webp&w=730"
    },
    {
      "slug": "rappahannock-animal-shelter-512017",
      "name": "Rappahannock Animal Shelter",
      "address": "160 Weaver Road, Amissville, VA 20106",
      "phone": "540-937-3336",
      "image": "https://cdn.findpawpal.com/office/512017.jpg?f=webp&w=730"
    },
    {
      "slug": "appomattox-county-animal-control-562131",
      "name": "Appomattox County Animal Control",
      "address": "PO Box 836, Appomattox, VA 24522",
      "phone": "804-352-7922",
      "image": "https://cdn.findpawpal.com/office/562131.jpg?f=webp&w=730"
    },
    {
      "slug": "our-critters-528925",
      "name": "Our Critters",
      "address": "PO Box 178, Ararat, VA 24053",
      "phone": "336-648-3781",
      "image": "https://cdn.findpawpal.com/office/528925.jpg?f=webp&w=730"
    },
    {
      "slug": "rescue-me-inc-animal-rescue-644535",
      "name": "Rescue Me, Inc., Animal Rescue",
      "address": "PO Box 534, Ark, VA 23003",
      "phone": "804-693-5997",
      "image": "https://cdn.findpawpal.com/office/644535.jpg?f=webp&w=730"
    },
    {
      "slug": "animal-welfare-league-of-arlington-706786",
      "name": "Animal Welfare League of Arlington",
      "address": "2650 South Arlington Mill Drive, Arlington, VA 22206",
      "phone": "703-931-9241",
      "image": "https://cdn.findpawpal.com/office/706786.jpg?f=webp&w=730"
    },
    {
      "slug": "arlington-animal-control-683165",
      "name": "Arlington Animal Control",
      "address": "822 North Kenmore Street, Arlington, VA 22201",
      "phone": "703-249-5066",
      "image": "https://cdn.findpawpal.com/office/683165.jpg?f=webp&w=730"
    },
    {
      "slug": "homeward-trails-animal-rescue-706787",
      "name": "Homeward Trails Animal Rescue",
      "address": "PO Box 100968, Arlington, VA 22210",
      "phone": "703-766-2647",
      "image": "https://cdn.findpawpal.com/office/706787.jpg?f=webp&w=730"
    },
    {
      "slug": "metro-ferals-555287",
      "name": "Metro Ferals",
      "address": "PO Box 7138, Arlington, VA 22207",
      "phone": "703-528-7782",
      "image": "https://cdn.findpawpal.com/office/555287.jpg?f=webp&w=730"
    },
    {
      "slug": "spca-of-northern-virginia-579533",
      "name": "SPCA of Northern Virginia",
      "address": "PO Box 100220, Arlington, VA 22210",
      "phone": "703-799-9390",
      "image": "https://cdn.findpawpal.com/office/579533.jpg?f=webp&w=730"
    },
    {
      "slug": "spca-of-nelson-county-682982",
      "name": "SPCA of Nelson County",
      "address": "PO Box 85, Arrington, VA 22922",
      "phone": "804-263-4378",
      "image": "https://cdn.findpawpal.com/office/682982.jpg?f=webp&w=730"
    },
    {
      "slug": "hanover-county-animal-control-561180",
      "name": "Hanover County Animal Control",
      "address": "12471 Taylor Complex Lane, Ashland, VA 23005",
      "phone": "804-365-6485",
      "image": "https://cdn.findpawpal.com/office/561180.jpg?f=webp&w=730"
    },
    {
      "slug": "hanover-humane-society-inc-682946",
      "name": "Hanover Humane Society, Inc.",
      "address": "12190 Washington Highway, Ashland, VA 23005",
      "phone": "804-798-0806",
      "image": "https://cdn.findpawpal.com/office/682946.jpg?f=webp&w=730"
    },
    {
      "slug": "hickory-hill-k-9-rescue-554339",
      "name": "Hickory Hill K-9 Rescue",
      "address": "PO Box 1505, Ashland, VA 23005",
      "phone": "804-537-5502",
      "image": "https://cdn.findpawpal.com/office/554339.jpg?f=webp&w=730"
    },
    {
      "slug": "indian-rivers-humane-society-578972",
      "name": "Indian Rivers Humane Society",
      "address": "PO Box 264, Aylett, VA 23009",
      "phone": "804-769-2145",
      "image": "https://cdn.findpawpal.com/office/578972.jpg?f=webp&w=730"
    },
    {
      "slug": "mecklenburg-county-animal-control-528847",
      "name": "Mecklenburg County Animal Control",
      "address": "819 Baskerville Road, Baskerville, VA 23915",
      "phone": "",
      "image": "https://cdn.findpawpal.com/office/528847.jpg?f=webp&w=730"
    },
    {
      "slug": "bedford-county-animal-control-511785",
      "name": "Bedford County Animal Control",
      "address": "122 East Main Street, Bedford, VA 24523",
      "phone": "540-586-7690",
      "image": "https://cdn.findpawpal.com/office/511785.jpg?f=webp&w=730"
    },
    {
      "slug": "bedford-humane-society-inc-644855",
      "name": "Bedford Humane Society Inc",
      "address": "829 Ole Turnpike Drive, Bedford, VA 24523",
      "phone": "540-586-6100",
      "image": "https://cdn.findpawpal.com/office/644855.jpg?f=webp&w=730"
    },
    {
      "slug": "animal-welfare-league-of-fairfax-county-644484",
      "name": "Animal Welfare League of Fairfax County",
      "address": "PO Box 820, Berryville, VA 22611",
      "phone": "",
      "image": "https://cdn.findpawpal.com/office/644484.jpg?f=webp&w=730"
    },
    {
      "slug": "clarke-county-animal-shelter-646746",
      "name": "Clarke County Animal Shelter",
      "address": "102 North Church Street, Berryville, VA 22611",
      "phone": "540-955-5104",
      "image": "https://cdn.findpawpal.com/office/646746.jpg?f=webp&w=730"
    },
    {
      "slug": "animal-care-new-river-valley-inc-706722",
      "name": "Animal Care New River Valley, Inc.",
      "address": "1 Squires Student Cente, Blacksburg, VA 24060",
      "phone": "540-522-7925",
      "image": "https://cdn.findpawpal.com/office/706722.jpg?f=webp&w=730"
    },
    {
      "slug": "northern-virginia-reptile-rescue-554776",
      "name": "Northern Virginia Reptile Rescue",
      "address": "PO Box 275, Bluemont, VA 20135",
      "phone": "703-971-1109",
      "image": "https://cdn.findpawpal.com/office/554776.jpg?f=webp&w=730"
    },
    {
      "slug": "peaceful-passings-inc-644515",
      "name": "Peaceful Passings, Inc.",
      "address": "2856 Cloverdale Road, Bremo Bluff, VA 23022",
      "phone": "434-842-3287",
      "image": "https://cdn.findpawpal.com/office/644515.jpg?f=webp&w=730"
    },
    {
      "slug": "bristol-city-animal-control-682868",
      "name": "Bristol City Animal Control",
      "address": "415 Cumberland Street, Bristol, VA 24201",
      "phone": "276-645-7400",
      "image": "https://cdn.findpawpal.com/office/682868.jpg?f=webp&w=730"
    },
    {
      "slug": "bristol-humane-society-646719",
      "name": "Bristol Humane Society",
      "address": "16222 Lee Highway, Bristol, VA 24202",
      "phone": "423-968-9136",
      "image": "https://cdn.findpawpal.com/office/646719.jpg?f=webp&w=730"
    },
    {
      "slug": "rocky-road-small-animal-rescue-560858",
      "name": "Rocky Road Small Animal Rescue",
      "address": "320 Buchanan Street, Bristol, VA 24201",
      "phone": "276-494-0236",
      "image": "https://cdn.findpawpal.com/office/560858.jpg?f=webp&w=730"
    },
    {
      "slug": "siberian-husky-assist-rescue-682870",
      "name": "Siberian Husky Assist Rescue",
      "address": "106 Bristol View Drive, Bristol, VA 24201",
      "phone": "276-494-3153",
      "image": "https://cdn.findpawpal.com/office/682870.jpg?f=webp&w=730"
    },
    {
      "slug": "siberian-husky-rescue-511769",
      "name": "Siberian Husky Rescue",
      "address": "8822 Rich Valley Road, Bristol, VA 24202",
      "phone": "276-696-2477",
      "image": "https://cdn.findpawpal.com/office/511769.jpg?f=webp&w=730"
    },
    {
      "slug": "buchanan-county-animal-shelter-579803",
      "name": "Buchanan County Animal Shelter",
      "address": "PO Box 252, Buckingham, VA 23921",
      "phone": "703-586-7690",
      "image": "https://cdn.findpawpal.com/office/579803.jpg?f=webp&w=730"
    },
    {
      "slug": "buckingham-animal-control-529648",
      "name": "Buckingham Animal Control",
      "address": "13360 West James Anderson Highway, Buckingham, VA 23921",
      "phone": "434-969-4242",
      "image": "https://cdn.findpawpal.com/office/529648.jpg?f=webp&w=730"
    },
    {
      "slug": "buena-vista-animal-control-578656",
      "name": "Buena Vista Animal Control",
      "address": "2039 Seymore Ave, Buena Vista, VA 24416",
      "phone": "540-261-6174",
      "image": "https://cdn.findpawpal.com/office/578656.jpg?f=webp&w=730"
    },
    {
      "slug": "white-bird-appaloosa-horse-rescue-575220",
      "name": "White Bird Appaloosa Horse Rescue",
      "address": "1688 Burke Tavern Road, Burkeville, VA 23922",
      "phone": "540-364-3452",
      "image": "https://cdn.findpawpal.com/office/575220.jpg?f=webp&w=730"
    },
    {
      "slug": "lost-fantasy-rescue-560853",
      "name": "Lost Fantasy Rescue",
      "address": "PO Box 42, Ceres, VA 24318",
      "phone": "276-682-3729",
      "image": "https://cdn.findpawpal.com/office/560853.jpg?f=webp&w=730"
    },
    {
      "slug": "a-forever-home-rescue-foundation-511932",
      "name": "A Forever Home Rescue Foundation",
      "address": "PO Box 222801, Chantilly, VA 20153",
      "phone": "703-961-8690",
      "image": "https://cdn.findpawpal.com/office/511932.jpg?f=webp&w=730"
    },
    {
      "slug": "collie-recue-inc-511171",
      "name": "Collie Recue, Inc.",
      "address": "PO Box 223953, Chantilly, VA 20153",
      "phone": "703-963-7329",
      "image": "https://cdn.findpawpal.com/office/511171.jpg?f=webp&w=730"
    },
    {
      "slug": "lost-dog-and-cat-rescue-foundation-575422",
      "name": "Lost Dog and Cat Rescue Foundation",
      "address": "PO Box 223953, Chantilly, VA 20153",
      "phone": "703-295-3647",
      "image": "https://cdn.findpawpal.com/office/575422.jpg?f=webp&w=730"
    },
    {
      "slug": "charles-city-county-animal-control-511097",
      "name": "Charles City County Animal Control",
      "address": "PO Box 128, Charles City, VA 23030",
      "phone": "888-788-5146",
      "image": "https://cdn.findpawpal.com/office/511097.jpg?f=webp&w=730"
    },
    {
      "slug": "charlotte-county-animal-control-706781",
      "name": "Charlotte County Animal Control",
      "address": "222 Law Lane, Charlotte Court House, VA 23923",
      "phone": "434-542-5141",
      "image": "https://cdn.findpawpal.com/office/706781.jpg?f=webp&w=730"
    },
    {
      "slug": "albemarle-county-animal-control-646880",
      "name": "Albemarle County Animal Control",
      "address": "1600 5TH STREET Ext, Charlottesville, VA 22902",
      "phone": "434-296-5807",
      "image": "https://cdn.findpawpal.com/office/646880.jpg?f=webp&w=730"
    },
    {
      "slug": "basset-rescue-of-old-dominion-579502",
      "name": "Basset Rescue of Old Dominion",
      "address": "3445 Seminole Trail, Charlottesville, VA 22911",
      "phone": "866-710-9476",
      "image": "https://cdn.findpawpal.com/office/579502.jpg?f=webp&w=730"
    },
    {
      "slug": "charlottesville-albemarle-spca-574612",
      "name": "Charlottesville Albemarle SPCA",
      "address": "3355 Berkmar Drive, Charlottesville, VA 22901",
      "phone": "434-973-5959",
      "image": "https://cdn.findpawpal.com/office/574612.jpg?f=webp&w=730"
    },
    {
      "slug": "heading-home-pug-rescue-644740",
      "name": "Heading Home Pug Rescue",
      "address": "220 South Main Street, Chatham, VA 24531",
      "phone": "434-203-7880",
      "image": "https://cdn.findpawpal.com/office/644740.jpg?f=webp&w=730"
    },
    {
      "slug": "pittsylvania-county-animal-control-575586",
      "name": "Pittsylvania County Animal Control",
      "address": "11 Main Street, Chatham, VA 24531",
      "phone": "434-432-7937",
      "image": "https://cdn.findpawpal.com/office/575586.jpg?f=webp&w=730"
    },
    {
      "slug": "adopt-a-spot-dalmatian-rescue-682883",
      "name": "Adopt A Spot Dalmatian Rescue",
      "address": "PO Box 9375, Chesapeake, VA 23321",
      "phone": "757-484-2940",
      "image": "https://cdn.findpawpal.com/office/682883.jpg?f=webp&w=730"
    },
    {
      "slug": "animal-assistance-league-of-virginia-inc-560920",
      "name": "Animal Assistance League of Virginia, Inc.",
      "address": "1149 New Mill Dr, Chesapeake, VA 23322",
      "phone": "757-548-0045",
      "image": "https://cdn.findpawpal.com/office/560920.jpg?f=webp&w=730"
    },
    {
      "slug": "chesapeake-city-animal-bureau-511102",
      "name": "Chesapeake City Animal Bureau",
      "address": "3807 Cook Blvd, Chesapeake, VA 23323",
      "phone": "757-382-8080",
      "image": "https://cdn.findpawpal.com/office/511102.jpg?f=webp&w=730"
    },
    {
      "slug": "chesapeake-humane-society-682884",
      "name": "Chesapeake Humane Society",
      "address": "PO Box 15061, Chesapeake, VA 23328",
      "phone": "787-490-4357",
      "image": "https://cdn.findpawpal.com/office/682884.jpg?f=webp&w=730"
    },
    {
      "slug": "collie-and-sheltie-rescue-of-southeast-virginia-706677",
      "name": "Collie and Sheltie Rescue of Southeast Virginia",
      "address": "2808 Meadow Wood Dr W, Chesapeake, VA 23321",
      "phone": "",
      "image": "https://cdn.findpawpal.com/office/706677.jpg?f=webp&w=730"
    },
    {
      "slug": "meower-power-feral-cat-coalition-554101",
      "name": "Meower Power Feral Cat Coalition",
      "address": "PO Box 9696, Chesapeake, VA 23321",
      "phone": "757-399-0001",
      "image": "https://cdn.findpawpal.com/office/554101.jpg?f=webp&w=730"
    },
    {
      "slug": "saving-animals-from-euthanasia-554113",
      "name": "Saving Animals From Euthanasia",
      "address": "PO Box 2483, Chester, VA 23831",
      "phone": "804-751-4501",
      "image": "https://cdn.findpawpal.com/office/554113.jpg?f=webp&w=730"
    },
    {
      "slug": "chesterfield-county-animal-control-646527",
      "name": "Chesterfield County Animal Control",
      "address": "PO Box 148, Chesterfield, VA 23832",
      "phone": "804-748-1683",
      "image": "https://cdn.findpawpal.com/office/646527.jpg?f=webp&w=730"
    },
    {
      "slug": "chesterfield-county-humane-society-554108",
      "name": "Chesterfield County Humane Society",
      "address": "PO Box 2916, Chesterfield, VA 23832",
      "phone": "804-717-6236",
      "image": "https://cdn.findpawpal.com/office/554108.jpg?f=webp&w=730"
    },
    {
      "slug": "humane-society-animal-shelter-528853",
      "name": "Humane Society Animal Shelter",
      "address": "1183 Flanagan Drive, Christiansburg, VA 24073",
      "phone": "540-382-1166",
      "image": "https://cdn.findpawpal.com/office/528853.jpg?f=webp&w=730"
    },
    {
      "slug": "montgomery-county-animal-control-646640",
      "name": "Montgomery County Animal Control",
      "address": "434 Cinnabar Road, Christiansburg, VA 24073",
      "phone": "540-382-5795",
      "image": "https://cdn.findpawpal.com/office/646640.jpg?f=webp&w=730"
    },
    {
      "slug": "virginia-partnership-for-animal-welfare-and-support-554458",
      "name": "Virginia Partnership for Animal Welfare and Support",
      "address": "PO Box 172, Christiansburg, VA 24068",
      "phone": "540-382-7297",
      "image": "https://cdn.findpawpal.com/office/554458.jpg?f=webp&w=730"
    },
    {
      "slug": "dickenson-county-animal-control-561664",
      "name": "Dickenson County Animal Control",
      "address": "PO Box 1098, Clintwood, VA 24228",
      "phone": "703-835-1320",
      "image": "https://cdn.findpawpal.com/office/561664.jpg?f=webp&w=730"
    },
    {
      "slug": "paws-of-southwest-virginia-inc-706757",
      "name": "PAWS of Southwest Virginia, Inc.",
      "address": "PO Box 576, Coeburn, VA 24230",
      "phone": "276-523-0222",
      "image": "https://cdn.findpawpal.com/office/706757.jpg?f=webp&w=730"
    },
    {
      "slug": "colonial-heights-animal-shelter-560972",
      "name": "Colonial Heights Animal Shelter",
      "address": "PO Box 3401, Colonial Heights, VA 23834",
      "phone": "804-526-9397",
      "image": "https://cdn.findpawpal.com/office/560972.jpg?f=webp&w=730"
    },
    {
      "slug": "spca-petersburg-and-colonial-heights-706682",
      "name": "SPCA Petersburg & Colonial Heights",
      "address": "201 Temple Ave, Colonial Heights, VA 23834",
      "phone": "804-526-7722",
      "image": "https://cdn.findpawpal.com/office/706682.jpg?f=webp&w=730"
    },
    {
      "slug": "central-virginia-horse-protection-association-644851",
      "name": "Central Virginia Horse Protection Association",
      "address": "626 Stonewall Road, Concord, VA 24538",
      "phone": "434-993-0666",
      "image": "https://cdn.findpawpal.com/office/644851.jpg?f=webp&w=730"
    },
    {
      "slug": "southampton-county-animal-control-683025",
      "name": "Southampton County Animal Control",
      "address": "21350 Plank Road, Courtland, VA 23837",
      "phone": "",
      "image": "https://cdn.findpawpal.com/office/683025.jpg?f=webp&w=730"
    },
    {
      "slug": "alleghany-county-animal-control-511460",
      "name": "Alleghany County Animal Control",
      "address": "265 West Main Street, Covington, VA 24426",
      "phone": "540-965-1770",
      "image": "https://cdn.findpawpal.com/office/511460.jpg?f=webp&w=730"
    },
    {
      "slug": "alleghany-humane-society-562093",
      "name": "Alleghany Humane Society",
      "address": "9313 Rich Patch Road, Covington, VA 24426",
      "phone": "540-862-2436",
      "image": "https://cdn.findpawpal.com/office/562093.jpg?f=webp&w=730"
    },
    {
      "slug": "covington-city-animal-control-644841",
      "name": "Covington City Animal Control",
      "address": "333 West Locust Street, Covington, VA 24426",
      "phone": "540-965-6333",
      "image": "https://cdn.findpawpal.com/office/644841.jpg?f=webp&w=730"
    },
    {
      "slug": "culpeper-county-animal-control-706783",
      "name": "Culpeper County Animal Control",
      "address": "10144 James Monroe Highway, Culpeper, VA 22701",
      "phone": "540-547-4477",
      "image": "https://cdn.findpawpal.com/office/706783.jpg?f=webp&w=730"
    },
    {
      "slug": "culpeper-county-humane-society-511157",
      "name": "Culpeper County Humane Society",
      "address": "PO Box 1224, Culpeper, VA 22701",
      "phone": "540-547-3556",
      "image": "https://cdn.findpawpal.com/office/511157.jpg?f=webp&w=730"
    },
    {
      "slug": "cumberland-spca-706683",
      "name": "Cumberland SPCA",
      "address": "PO Box 276, Cumberland, VA 23040",
      "phone": "804-492-4740",
      "image": "https://cdn.findpawpal.com/office/706683.jpg?f=webp&w=730"
    },
    {
      "slug": "danville-animal-control-578741",
      "name": "Danville Animal Control",
      "address": "PO Box 3300, Danville, VA 24543",
      "phone": "804-799-6517",
      "image": "https://cdn.findpawpal.com/office/578741.jpg?f=webp&w=730"
    },
    {
      "slug": "danville-area-humane-society-706684",
      "name": "Danville Area Humane Society",
      "address": "1000 S Boston Rd, Danville, VA 24540",
      "phone": "804-799-0843",
      "image": "https://cdn.findpawpal.com/office/706684.jpg?f=webp&w=730"
    },
    {
      "slug": "mosby-foundation-683080",
      "name": "Mosby Foundation",
      "address": "415 N Coalter St, Deerfield, VA 24432",
      "phone": "540-939-4035",
      "image": "https://cdn.findpawpal.com/office/683080.jpg?f=webp&w=730"
    },
    {
      "slug": "beath-animal-shelter-511064",
      "name": "Beath Animal Shelter",
      "address": "PO Box 628, Dillwyn, VA 23936",
      "phone": "434-983-7387",
      "image": "https://cdn.findpawpal.com/office/511064.jpg?f=webp&w=730"
    },
    {
      "slug": "healing-hands-sanctuary-574586",
      "name": "Healing Hands Sanctuary",
      "address": "PO Box 3840, Dillwyn, VA 23936",
      "phone": "434-983-7766",
      "image": "https://cdn.findpawpal.com/office/574586.jpg?f=webp&w=730"
    },
    {
      "slug": "dinwiddie-county-animal-shelter-575396",
      "name": "Dinwiddie County Animal Shelter",
      "address": "PO Box 70, Dinwiddie, VA 23841",
      "phone": "804-469-3759",
      "image": "https://cdn.findpawpal.com/office/575396.jpg?f=webp&w=730"
    },
    {
      "slug": "hopewell-humane-society-529265",
      "name": "Hopewell Humane Society",
      "address": "18201 Wards Creek Road, Disputanta, VA 23842",
      "phone": "804-458-7303",
      "image": "https://cdn.findpawpal.com/office/529265.jpg?f=webp&w=730"
    },
    {
      "slug": "prince-george-county-animal-control-644823",
      "name": "Prince George County Animal Control",
      "address": "8391 County Drive, Disputanta, VA 23842",
      "phone": "804-991-3200",
      "image": "https://cdn.findpawpal.com/office/644823.jpg?f=webp&w=730"
    },
    {
      "slug": "pulaski-county-humane-society-646683",
      "name": "Pulaski County Humane Society",
      "address": "80 Dublin Park Road, Dublin, VA 24084",
      "phone": "540-674-0089",
      "image": "https://cdn.findpawpal.com/office/646683.jpg?f=webp&w=730"
    },
    {
      "slug": "brew-inc-529171",
      "name": "BREW, Inc.",
      "address": "5171 Waterway Drive, Dumfries, VA 22025",
      "phone": "703-832-8697",
      "image": "https://cdn.findpawpal.com/office/529171.jpg?f=webp&w=730"
    },
    {
      "slug": "westie-rescue-of-the-mid-atlantic-states-inc-579610",
      "name": "Westie Rescue of the Mid-Atlantic States, Inc.",
      "address": "PO Box 342, Dunn Loring, VA 22027",
      "phone": "703-671-1039",
      "image": "https://cdn.findpawpal.com/office/579610.jpg?f=webp&w=730"
    },
    {
      "slug": "alleghany-highlands-all-breed-rescue-inc-554878",
      "name": "Alleghany Highlands All Breed Rescue, Inc.",
      "address": "6252 McKinney Hollow Road, Eagle Rock, VA 24085",
      "phone": "540-968-2612",
      "image": "https://cdn.findpawpal.com/office/554878.jpg?f=webp&w=730"
    },
    {
      "slug": "northampton-county-animal-control-574976",
      "name": "Northampton County Animal Control",
      "address": "PO Box 386, Eastville, VA 23347",
      "phone": "",
      "image": "https://cdn.findpawpal.com/office/574976.jpg?f=webp&w=730"
    },
    {
      "slug": "shenandoah-county-animal-shelter-561820",
      "name": "Shenandoah County Animal Shelter",
      "address": "268 Landfill Road, Edinburg, VA 22824",
      "phone": "540-984-8955",
      "image": "https://cdn.findpawpal.com/office/561820.jpg?f=webp&w=730"
    },
    {
      "slug": "surry-county-animal-control-575554",
      "name": "Surry County Animal Control",
      "address": "265 Old Burrough Road, Elberon, VA 23846",
      "phone": "757-294-0158",
      "image": "https://cdn.findpawpal.com/office/575554.jpg?f=webp&w=730"
    },
    {
      "slug": "emporia-animal-control-511166",
      "name": "Emporia Animal Control",
      "address": "1443 James River Junction, Emporia, VA 23847",
      "phone": "804-634-3609",
      "image": "https://cdn.findpawpal.com/office/511166.jpg?f=webp&w=730"
    },
    {
      "slug": "greensville-county-animal-shelter-683160",
      "name": "Greensville County Animal Shelter",
      "address": "1750 E Atlantic St, Emporia, VA 23847",
      "phone": "434-348-3379",
      "image": "https://cdn.findpawpal.com/office/683160.jpg?f=webp&w=730"
    },
    {
      "slug": "city-of-fairfax-animal-control-shelter-644765",
      "name": "City of Fairfax Animal Control Shelter",
      "address": "3730 Old Lee Highway, Fairfax, VA 22030",
      "phone": "703-385-7919",
      "image": "https://cdn.findpawpal.com/office/644765.jpg?f=webp&w=730"
    },
    {
      "slug": "fairfax-county-animal-shelter-561867",
      "name": "Fairfax County Animal Shelter",
      "address": "4500 West Ox Road, Fairfax, VA 22030",
      "phone": "703-830-1100",
      "image": "https://cdn.findpawpal.com/office/561867.jpg?f=webp&w=730"
    },
    {
      "slug": "humane-society-of-fairfax-county-578774",
      "name": "Humane Society of Fairfax County",
      "address": "4057 Chain Bridge Road, Fairfax, VA 22030",
      "phone": "703-385-7387",
      "image": "https://cdn.findpawpal.com/office/578774.jpg?f=webp&w=730"
    },
    {
      "slug": "mutt-love-rescue-inc-578783",
      "name": "Mutt Love Rescue, Inc.",
      "address": "PO Box 1005, Fairfax, VA 22038",
      "phone": "",
      "image": "https://cdn.findpawpal.com/office/578783.jpg?f=webp&w=730"
    },
    {
      "slug": "the-shiloh-project-706799",
      "name": "The Shiloh Project",
      "address": "12210 Fairfax Towne Center, Fairfax, VA 22033",
      "phone": "703-591-3600",
      "image": "https://cdn.findpawpal.com/office/706799.jpg?f=webp&w=730"
    },
    {
      "slug": "animal-allies-burke-alexandria-511927",
      "name": "Animal Allies Burke Alexandria",
      "address": "PO Box 7040, Fairfax Station, VA 22039",
      "phone": "703-940-9183",
      "image": "https://cdn.findpawpal.com/office/511927.jpg?f=webp&w=730"
    },
    {
      "slug": "fairfax-station-animal-control-529639",
      "name": "Fairfax Station Animal Control",
      "address": "7647 Clifton Road, Fairfax Station, VA 22039",
      "phone": "703-978-4462",
      "image": "https://cdn.findpawpal.com/office/529639.jpg?f=webp&w=730"
    },
    {
      "slug": "homeless-animals-rescue-team-646829",
      "name": "Homeless Animals Rescue Team",
      "address": "PO Box 7261, Fairfax Station, VA 22039",
      "phone": "703-691-4278",
      "image": "https://cdn.findpawpal.com/office/646829.jpg?f=webp&w=730"
    },
    {
      "slug": "rockbridge-county-animal-control-561476",
      "name": "Rockbridge County Animal Control",
      "address": "PO Box 3, Fairfield, VA 24435",
      "phone": "",
      "image": "https://cdn.findpawpal.com/office/561476.jpg?f=webp&w=730"
    },
    {
      "slug": "ferrets-r-no-1-shelter-and-rescue-511972",
      "name": "Ferrets R No 1 Shelter & Rescue",
      "address": "5906 Boston Drive, Falls Church, VA 22041",
      "phone": "703-998-3151",
      "image": "https://cdn.findpawpal.com/office/511972.jpg?f=webp&w=730"
    },
    {
      "slug": "golden-retriever-rescue-education-and-training-inc-555057",
      "name": "Golden Retriever Rescue Education and Training, Inc.",
      "address": "PO Box 3069, Falls Church, VA 22043",
      "phone": "703-620-6593",
      "image": "https://cdn.findpawpal.com/office/555057.jpg?f=webp&w=730"
    },
    {
      "slug": "the-pet-haven-rescue-center-inc-561799",
      "name": "The Pet Haven Rescue Center, Inc.",
      "address": "PO Box 24, Falls Mills, VA 24613",
      "phone": "276-326-3483",
      "image": "https://cdn.findpawpal.com/office/561799.jpg?f=webp&w=730"
    },
    {
      "slug": "farmville-animal-control-512125",
      "name": "Farmville Animal Control",
      "address": "252 County Shop Road, Farmville, VA 23901",
      "phone": "434-223-7310",
      "image": "https://cdn.findpawpal.com/office/512125.jpg?f=webp&w=730"
    },
    {
      "slug": "botefourt-county-animal-control-706777",
      "name": "Botefourt County Animal Control",
      "address": "PO Box 18, Fincastle, VA 24090",
      "phone": "540-473-8030",
      "image": "https://cdn.findpawpal.com/office/706777.jpg?f=webp&w=730"
    },
    {
      "slug": "floyd-county-animal-control-575464",
      "name": "Floyd County Animal Control",
      "address": "110 Newtown Road Northeast, Floyd, VA 24091",
      "phone": "540-745-9365",
      "image": "https://cdn.findpawpal.com/office/575464.jpg?f=webp&w=730"
    },
    {
      "slug": "floyd-county-humane-society-646559",
      "name": "Floyd County Humane Society",
      "address": "PO Box 862, Floyd, VA 24091",
      "phone": "540-745-7207",
      "image": "https://cdn.findpawpal.com/office/646559.jpg?f=webp&w=730"
    },
    {
      "slug": "brook-hill-restoration-inc-561676",
      "name": "Brook Hill Restoration Inc",
      "address": "7289 Bellevue Road, Forest, VA 24551",
      "phone": "540-586-7432",
      "image": "https://cdn.findpawpal.com/office/561676.jpg?f=webp&w=730"
    },
    {
      "slug": "shenandoah-small-dog-rescue-575382",
      "name": "Shenandoah Small Dog Rescue",
      "address": "871 South Fort Valley Road, Fort Valley, VA 22652",
      "phone": "540-933-6257",
      "image": "https://cdn.findpawpal.com/office/575382.jpg?f=webp&w=730"
    },
    {
      "slug": "franklin-animal-shelter-706694",
      "name": "Franklin Animal Shelter",
      "address": "100 S Main St, Franklin, VA 23851",
      "phone": "757-562-8575",
      "image": "https://cdn.findpawpal.com/office/706694.jpg?f=webp&w=730"
    },
    {
      "slug": "humane-society-of-franklin-528621",
      "name": "Humane Society of Franklin",
      "address": "27463 Pretlow Road, Franklin, VA 23851",
      "phone": "757-562-2510",
      "image": "https://cdn.findpawpal.com/office/528621.jpg?f=webp&w=730"
    },
    {
      "slug": "fredericksburg-spca-578849",
      "name": "Fredericksburg SPCA",
      "address": "1523 Old William Street, Fredericksburg, VA 22401",
      "phone": "540-373-9008",
      "image": "https://cdn.findpawpal.com/office/578849.jpg?f=webp&w=730"
    },
    {
      "slug": "rappahannock-humane-society-646837",
      "name": "Rappahannock Humane Society",
      "address": "PO Box 8313, Fredericksburg, VA 22404",
      "phone": "540-785-1470",
      "image": "https://cdn.findpawpal.com/office/646837.jpg?f=webp&w=730"
    },
    {
      "slug": "spotsylvania-county-animal-control-554649",
      "name": "Spotsylvania County Animal Control",
      "address": "450 Tv Drive, Fredericksburg, VA 22408",
      "phone": "540-507-7450",
      "image": "https://cdn.findpawpal.com/office/554649.jpg?f=webp&w=730"
    },
    {
      "slug": "whiskers-n-wags-rescue-team-inc-579624",
      "name": "Whiskers-N-Wags Rescue Team, Inc.",
      "address": "PO Box 41154, Fredericksburg, VA 22404",
      "phone": "",
      "image": "https://cdn.findpawpal.com/office/579624.jpg?f=webp&w=730"
    },
    {
      "slug": "humane-society-of-warren-county-683066",
      "name": "Humane Society of Warren County",
      "address": "1245 Progress Drive, Front Royal, VA 22630",
      "phone": "540-635-4734",
      "image": "https://cdn.findpawpal.com/office/683066.jpg?f=webp&w=730"
    },
    {
      "slug": "galax-animal-shelter-644724",
      "name": "Galax Animal Shelter",
      "address": "201 Fairview Road, Galax, VA 24333",
      "phone": "",
      "image": "https://cdn.findpawpal.com/office/644724.jpg?f=webp&w=730"
    },
    {
      "slug": "galax-carroll-grayson-spca-706698",
      "name": "Galax Carroll Grayson SPCA",
      "address": "PO Box 2308, Galax, VA 24333",
      "phone": "540-236-8501",
      "image": "https://cdn.findpawpal.com/office/706698.jpg?f=webp&w=730"
    },
    {
      "slug": "scott-county-animal-control-575192",
      "name": "Scott County Animal Control",
      "address": "112 East Water Street, Gate City, VA 24251",
      "phone": "",
      "image": "https://cdn.findpawpal.com/office/575192.jpg?f=webp&w=730"
    },
    {
      "slug": "saving-furry-friends-529114",
      "name": "Saving Furry Friends",
      "address": "PO Box 741, Glade Spring, VA 24340",
      "phone": "276-706-6477",
      "image": "https://cdn.findpawpal.com/office/529114.jpg?f=webp&w=730"
    },
    {
      "slug": "friends-united-with-the-richmond-shelter-646780",
      "name": "Friends United with the Richmond Shelter",
      "address": "4660 Pouncey Tract Road, Glen Allen, VA 23059",
      "phone": "804-364-1944",
      "image": "https://cdn.findpawpal.com/office/646780.jpg?f=webp&w=730"
    },
    {
      "slug": "pet-harbor-rescue-and-referral-561760",
      "name": "Pet Harbor Rescue & Referral",
      "address": "PO Box 1502, Glen Allen, VA 23060",
      "phone": "703-583-4759",
      "image": "https://cdn.findpawpal.com/office/561760.jpg?f=webp&w=730"
    },
    {
      "slug": "gloucester-animal-control-578883",
      "name": "Gloucester Animal Control",
      "address": "6504 Main Street, Gloucester Courthouse, VA 23061",
      "phone": "804-693-5290",
      "image": "https://cdn.findpawpal.com/office/578883.jpg?f=webp&w=730"
    },
    {
      "slug": "gloucester-animal-control-646869",
      "name": "Gloucester Animal Control",
      "address": "6504 Main Street, Gloucester Courthouse, VA 23061",
      "phone": "804-693-5290",
      "image": "https://cdn.findpawpal.com/office/646869.jpg?f=webp&w=730"
    },
    {
      "slug": "gloucester-mathews-humane-society-528664",
      "name": "Gloucester-Mathews Humane Society",
      "address": "6620 Jackson Lane, Gloucester Courthouse, VA 23061",
      "phone": "804-693-5520",
      "image": "https://cdn.findpawpal.com/office/528664.jpg?f=webp&w=730"
    },
    {
      "slug": "goochland-county-animal-control-528693",
      "name": "Goochland County Animal Control",
      "address": "PO Box 10, Goochland, VA 23063",
      "phone": "804-556-5302",
      "image": "https://cdn.findpawpal.com/office/528693.jpg?f=webp&w=730"
    },
    {
      "slug": "buchanan-county-humane-society-682872",
      "name": "Buchanan County Humane Society",
      "address": "PO Box 758, Grundy, VA 24614",
      "phone": "703-935-7200",
      "image": "https://cdn.findpawpal.com/office/682872.jpg?f=webp&w=730"
    },
    {
      "slug": "buckingham-county-animal-control-579349",
      "name": "Buckingham County Animal Control",
      "address": "PO Box 950, Grundy, VA 24614",
      "phone": "276-935-6580",
      "image": "https://cdn.findpawpal.com/office/579349.jpg?f=webp&w=730"
    },
    {
      "slug": "pet-rescue-foundation-706703",
      "name": "Pet Rescue Foundation",
      "address": "PO Box 70, Hadensville, VA 23067",
      "phone": "804-627-6066",
      "image": "https://cdn.findpawpal.com/office/706703.jpg?f=webp&w=730"
    },
    {
      "slug": "halifax-county-animal-control-511310",
      "name": "Halifax County Animal Control",
      "address": "PO Box 786, Halifax, VA 24558",
      "phone": "804-572-6162",
      "image": "https://cdn.findpawpal.com/office/511310.jpg?f=webp&w=730"
    },
    {
      "slug": "no-kill-dog-shelter-706706",
      "name": "No Kill Dog Shelter",
      "address": "80 Butler Farm Road, Hampton, VA 23666",
      "phone": "",
      "image": "https://cdn.findpawpal.com/office/706706.jpg?f=webp&w=730"
    },
    {
      "slug": "reptile-rescue-ranch-of-virginia-578902",
      "name": "Reptile Rescue Ranch of Virginia",
      "address": "1521 Denton Dr, Hampton, VA 23664",
      "phone": "757-268-1770",
      "image": "https://cdn.findpawpal.com/office/578902.jpg?f=webp&w=730"
    },
    {
      "slug": "the-cat-corner-574819",
      "name": "The Cat Corner",
      "address": "85 Fulton St, Hampton, VA 23663",
      "phone": "757-722-0590",
      "image": "https://cdn.findpawpal.com/office/574819.jpg?f=webp&w=730"
    },
    {
      "slug": "roanoke-valley-horse-rescue-574754",
      "name": "Roanoke Valley Horse Rescue",
      "address": "1725 Edwardsville Road, Hardy, VA 24101",
      "phone": "540-797-1999",
      "image": "https://cdn.findpawpal.com/office/574754.jpg?f=webp&w=730"
    },
    {
      "slug": "cats-cradle-511349",
      "name": "Cat's Cradle",
      "address": "PO Box 2152, Harrisonburg, VA 22801",
      "phone": "540-438-5222",
      "image": "https://cdn.findpawpal.com/office/511349.jpg?f=webp&w=730"
    },
    {
      "slug": "harrisonburg-animal-control-574837",
      "name": "Harrisonburg Animal Control",
      "address": "181 South Liberty Street, Harrisonburg, VA 22801",
      "phone": "540-434-2317",
      "image": "https://cdn.findpawpal.com/office/574837.jpg?f=webp&w=730"
    },
    {
      "slug": "rockingham-harrisonburg-spca-528749",
      "name": "Rockingham/Harrisonburg SPCA",
      "address": "2170 Old Furnace Road, Harrisonburg, VA 22802",
      "phone": "540-434-5270",
      "image": "https://cdn.findpawpal.com/office/528749.jpg?f=webp&w=730"
    },
    {
      "slug": "virginia-federation-of-humane-societies-682953",
      "name": "Virginia Federation of Humane Societies",
      "address": "826 Oakwood Drive, Harrisonburg, VA 22801",
      "phone": "540-879-9874",
      "image": "https://cdn.findpawpal.com/office/682953.jpg?f=webp&w=730"
    },
    {
      "slug": "northumberland-county-animal-control-529608",
      "name": "Northumberland County Animal Control",
      "address": "11703 Northumberland Highway, Heathsville, VA 22473",
      "phone": "804-580-6156",
      "image": "https://cdn.findpawpal.com/office/529608.jpg?f=webp&w=730"
    },
    {
      "slug": "fancy-cats-rescue-team-554166",
      "name": "Fancy Cats Rescue Team",
      "address": "PO Box 182, Herndon, VA 20172",
      "phone": "703-464-0760",
      "image": "https://cdn.findpawpal.com/office/554166.jpg?f=webp&w=730"
    },
    {
      "slug": "furry-suits-rescue-706689",
      "name": "Furry Suits Rescue",
      "address": "PO Box 21, Herndon, VA 20172",
      "phone": "",
      "image": "https://cdn.findpawpal.com/office/706689.jpg?f=webp&w=730"
    },
    {
      "slug": "humane-farm-animal-care-574699",
      "name": "Humane Farm Animal Care",
      "address": "PO Box 727, Herndon, VA 20172",
      "phone": "703-435-3883",
      "image": "https://cdn.findpawpal.com/office/574699.jpg?f=webp&w=730"
    },
    {
      "slug": "rescuing-animals-in-need-579462",
      "name": "Rescuing Animals In Need",
      "address": "PO Box 217, Highland Springs, VA 23075",
      "phone": "804-747-1155",
      "image": "https://cdn.findpawpal.com/office/579462.jpg?f=webp&w=730"
    },
    {
      "slug": "hopewell-animal-control-682956",
      "name": "Hopewell Animal Control",
      "address": "300 N Main St, Hopewell, VA 23860",
      "phone": "",
      "image": "https://cdn.findpawpal.com/office/682956.jpg?f=webp&w=730"
    },
    {
      "slug": "bath-animal-welfare-foundation-579841",
      "name": "Bath Animal Welfare Foundation",
      "address": "9295 Sam Snead Highway, Hot Springs, VA 24445",
      "phone": "540-839-8666",
      "image": "https://cdn.findpawpal.com/office/579841.jpg?f=webp&w=730"
    },
    {
      "slug": "bath-county-animal-shelter-706828",
      "name": "Bath County Animal Shelter",
      "address": "1164 Virginia Avenue, Hot Springs, VA 24445",
      "phone": "540-839-7210",
      "image": "https://cdn.findpawpal.com/office/706828.jpg?f=webp&w=730"
    },
    {
      "slug": "lee-county-animal-control-574876",
      "name": "Lee County Animal Control",
      "address": "PO Box 367, Jonesville, VA 24263",
      "phone": "276-346-7710",
      "image": "https://cdn.findpawpal.com/office/574876.jpg?f=webp&w=730"
    },
    {
      "slug": "animal-welfare-league-inc-579355",
      "name": "Animal Welfare League, Inc.",
      "address": "75 North Main Street, Kilmarnock, VA 22482",
      "phone": "804-435-0822",
      "image": "https://cdn.findpawpal.com/office/579355.jpg?f=webp&w=730"
    },
    {
      "slug": "king-george-animal-rescue-league-579434",
      "name": "King George Animal Rescue League",
      "address": "PO Box 1143, King George, VA 22485",
      "phone": "540-644-0110",
      "image": "https://cdn.findpawpal.com/office/579434.jpg?f=webp&w=730"
    },
    {
      "slug": "lancaster-county-animal-shelter-511383",
      "name": "Lancaster County Animal Shelter",
      "address": "3156 Regina Road, Lancaster, VA 22503",
      "phone": "804-462-7175",
      "image": "https://cdn.findpawpal.com/office/511383.jpg?f=webp&w=730"
    },
    {
      "slug": "brunswick-county-animal-shelter-554031",
      "name": "Brunswick County Animal Shelter",
      "address": "595 Planters Road, Lawrenceville, VA 23868",
      "phone": "434-848-0912",
      "image": "https://cdn.findpawpal.com/office/554031.jpg?f=webp&w=730"
    },
    {
      "slug": "russell-county-animal-control-706745",
      "name": "Russell County Animal Control",
      "address": "PO Box 1208, Lebanon, VA 24266",
      "phone": "703-889-5871",
      "image": "https://cdn.findpawpal.com/office/706745.jpg?f=webp&w=730"
    },
    {
      "slug": "doo-doo-happens-rescue-511406",
      "name": "Doo Doo Happens Rescue",
      "address": "704 Godfrey Court Southeast, Leesburg, VA 20175",
      "phone": "703-213-5841",
      "image": "https://cdn.findpawpal.com/office/511406.jpg?f=webp&w=730"
    },
    {
      "slug": "equine-rescue-league-inc-706717",
      "name": "Equine Rescue League, Inc.",
      "address": "PO Box 4366, Leesburg, VA 20177",
      "phone": "703-771-1240",
      "image": "https://cdn.findpawpal.com/office/706717.jpg?f=webp&w=730"
    },
    {
      "slug": "humane-society-of-loudon-county-511401",
      "name": "Humane Society of Loudon County",
      "address": "PO Box 601, Leesburg, VA 20178",
      "phone": "703-777-2912",
      "image": "https://cdn.findpawpal.com/office/511401.jpg?f=webp&w=730"
    },
    {
      "slug": "rockbridge-spca-644714",
      "name": "Rockbridge SPCA",
      "address": "10 Animal Place, Lexington, VA 24450",
      "phone": "540-463-5123",
      "image": "https://cdn.findpawpal.com/office/644714.jpg?f=webp&w=730"
    },
    {
      "slug": "humane-society-of-nelson-county-528873",
      "name": "Humane Society of Nelson County",
      "address": "29 Stagebridge Road, Lovingston, VA 22949",
      "phone": "804-263-7722",
      "image": "https://cdn.findpawpal.com/office/528873.jpg?f=webp&w=730"
    },
    {
      "slug": "lunenburg-county-animal-control-529594",
      "name": "Lunenburg County Animal Control",
      "address": "160 Courthouse Sq, Lunenburg, VA 23974",
      "phone": "434-696-4452",
      "image": "https://cdn.findpawpal.com/office/529594.jpg?f=webp&w=730"
    },
    {
      "slug": "page-county-animal-control-555152",
      "name": "Page County Animal Control",
      "address": "108 South Court Street, Luray, VA 22835",
      "phone": "540-743-4398",
      "image": "https://cdn.findpawpal.com/office/555152.jpg?f=webp&w=730"
    },
    {
      "slug": "lynchburg-animal-control-706719",
      "name": "Lynchburg Animal Control",
      "address": "PO Box 199, Lynchburg, VA 24505",
      "phone": "",
      "image": "https://cdn.findpawpal.com/office/706719.jpg?f=webp&w=730"
    },
    {
      "slug": "lynchburg-humane-society-528818",
      "name": "Lynchburg Humane Society",
      "address": "3305 Naval Reserve Rd, Lynchburg, VA 24501",
      "phone": "434-846-1438",
      "image": "https://cdn.findpawpal.com/office/528818.jpg?f=webp&w=730"
    },
    {
      "slug": "shenandoah-valley-animal-control-683150",
      "name": "Shenandoah Valley Animal Control",
      "address": "1001 Mount Torrey Road, Lyndhurst, VA 22952",
      "phone": "540-943-5142",
      "image": "https://cdn.findpawpal.com/office/683150.jpg?f=webp&w=730"
    },
    {
      "slug": "madison-county-animal-control-644584",
      "name": "Madison County Animal Control",
      "address": "PO Box 705, Madison, VA 22727",
      "phone": "",
      "image": "https://cdn.findpawpal.com/office/644584.jpg?f=webp&w=730"
    },
    {
      "slug": "manassas-city-animal-control-562014",
      "name": "Manassas City Animal Control",
      "address": "10039 Dean Dr, Manassas, VA 20110",
      "phone": "703-257-2420",
      "image": "https://cdn.findpawpal.com/office/562014.jpg?f=webp&w=730"
    },
    {
      "slug": "northern-virginia-animal-league-inc-706739",
      "name": "Northern Virginia Animal League, Inc.",
      "address": "7522 Hyde Court, Manassas, VA 20109",
      "phone": "703-368-2460",
      "image": "https://cdn.findpawpal.com/office/706739.jpg?f=webp&w=730"
    },
    {
      "slug": "prince-william-county-animal-control-bureau-511572",
      "name": "Prince William County Animal Control Bureau",
      "address": "14807 Dumfries Road, Manassas, VA 20112",
      "phone": "703-792-6465",
      "image": "https://cdn.findpawpal.com/office/511572.jpg?f=webp&w=730"
    },
    {
      "slug": "manassas-park-animal-control-561284",
      "name": "Manassas Park Animal Control",
      "address": "329 Manassas Dr, Manassas Park, VA 20111",
      "phone": "",
      "image": "https://cdn.findpawpal.com/office/561284.jpg?f=webp&w=730"
    },
    {
      "slug": "smyth-county-animal-shelter-561671",
      "name": "Smyth County Animal Shelter",
      "address": "287 Fox Valley Road, Marion, VA 24354",
      "phone": "276-646-2222",
      "image": "https://cdn.findpawpal.com/office/561671.jpg?f=webp&w=730"
    },
    {
      "slug": "smyth-county-humane-society-561480",
      "name": "Smyth County Humane Society",
      "address": "PO Box 1124, Marion, VA 24354",
      "phone": "",
      "image": "https://cdn.findpawpal.com/office/561480.jpg?f=webp&w=730"
    },
    {
      "slug": "henry-county-animal-control-554361",
      "name": "Henry County Animal Control",
      "address": "3250 Kings Mountain Road, Martinsville, VA 24112",
      "phone": "276-656-4266",
      "image": "https://cdn.findpawpal.com/office/554361.jpg?f=webp&w=730"
    },
    {
      "slug": "spca-of-martinsville-henry-county-646759",
      "name": "SPCA of Martinsville-Henry County",
      "address": "132 Joseph Martin Highway, Martinsville, VA 24112",
      "phone": "276-638-7297",
      "image": "https://cdn.findpawpal.com/office/646759.jpg?f=webp&w=730"
    },
    {
      "slug": "animal-care-of-mathews-646635",
      "name": "Animal Care of Mathews",
      "address": "241 Main Street, Mathews, VA 23109",
      "phone": "804-725-5242",
      "image": "https://cdn.findpawpal.com/office/646635.jpg?f=webp&w=730"
    },
    {
      "slug": "blue-ridge-border-collie-rescue-646828",
      "name": "Blue Ridge Border Collie Rescue",
      "address": "1950 Kirby Road, McLean, VA 22101",
      "phone": "571-766-0980",
      "image": "https://cdn.findpawpal.com/office/646828.jpg?f=webp&w=730"
    },
    {
      "slug": "smittys-cat-rescue-574834",
      "name": "Smitty's Cat Rescue",
      "address": "9349 Ravensworth Court, Mechanicsville, VA 23116",
      "phone": "804-852-3993",
      "image": "https://cdn.findpawpal.com/office/574834.jpg?f=webp&w=730"
    },
    {
      "slug": "southside-spca-554578",
      "name": "Southside SPCA",
      "address": "PO Box 66, Meherrin, VA 23954",
      "phone": "434-736-9595",
      "image": "https://cdn.findpawpal.com/office/554578.jpg?f=webp&w=730"
    },
    {
      "slug": "accomack-county-animal-control-706813",
      "name": "Accomack County Animal Control",
      "address": "28167 Beacon Road, Melfa, VA 23410",
      "phone": "757-787-7091",
      "image": "https://cdn.findpawpal.com/office/706813.jpg?f=webp&w=730"
    },
    {
      "slug": "4-paws-rescue-team-inc-706686",
      "name": "4 PAWS Rescue Team, Inc.",
      "address": "PO Box 2908, Merrifield, VA 22116",
      "phone": "703-715-6369",
      "image": "https://cdn.findpawpal.com/office/706686.jpg?f=webp&w=730"
    },
    {
      "slug": "feline-foundation-of-greater-washington-511985",
      "name": "Feline Foundation of Greater Washington",
      "address": "PO Box 3071, Merrifield, VA 22116",
      "phone": "703-920-8665",
      "image": "https://cdn.findpawpal.com/office/511985.jpg?f=webp&w=730"
    },
    {
      "slug": "mans-best-friends-inc-706718",
      "name": "Man's Best Friends, Inc.",
      "address": "PO Box 1841, Middleburg, VA 20118",
      "phone": "703-581-1128",
      "image": "https://cdn.findpawpal.com/office/706718.jpg?f=webp&w=730"
    },
    {
      "slug": "spca-animal-shelter-528597",
      "name": "SPCA Animal Shelter",
      "address": "9350 Rogues Road, Midland, VA 22728",
      "phone": "540-788-9000",
      "image": "https://cdn.findpawpal.com/office/528597.jpg?f=webp&w=730"
    },
    {
      "slug": "caroline-county-animal-shelter-529355",
      "name": "Caroline County Animal Shelter",
      "address": "14080 Devils 3 Jump Road, Milford, VA 22514",
      "phone": "804-633-9041",
      "image": "https://cdn.findpawpal.com/office/529355.jpg?f=webp&w=730"
    },
    {
      "slug": "rescue-me-pet-rescue-575263",
      "name": "Rescue Me Pet Rescue",
      "address": "1145 Cranberry Court, Moneta, VA 24121",
      "phone": "804-986-3647",
      "image": "https://cdn.findpawpal.com/office/575263.jpg?f=webp&w=730"
    },
    {
      "slug": "animal-shelter-646720",
      "name": "Animal Shelter",
      "address": "6154 Stratford Hall Road, Montross, VA 22520",
      "phone": "804-493-0869",
      "image": "https://cdn.findpawpal.com/office/646720.jpg?f=webp&w=730"
    },
    {
      "slug": "dc-metro-no-more-homeless-pets-683116",
      "name": "Dc Metro No More Homeless Pets",
      "address": "PO Box 19, Mount Vernon, VA 22121",
      "phone": "703-207-1386",
      "image": "https://cdn.findpawpal.com/office/683116.jpg?f=webp&w=730"
    },
    {
      "slug": "giles-county-humane-society-644533",
      "name": "Giles County Humane Society",
      "address": "251 State Line Road, Narrows, VA 24124",
      "phone": "",
      "image": "https://cdn.findpawpal.com/office/644533.jpg?f=webp&w=730"
    },
    {
      "slug": "craig-county-animal-control-579536",
      "name": "Craig County Animal Control",
      "address": "PO Box 308, New Castle, VA 24127",
      "phone": "540-864-5010",
      "image": "https://cdn.findpawpal.com/office/579536.jpg?f=webp&w=730"
    },
    {
      "slug": "obg-cocker-spaniel-rescue-of-northern-virginia-oldies-but-goodies-511975",
      "name": "Obg Cocker Spaniel Rescue of Northern Virginia Oldies But Goodies",
      "address": "PO Box 361, Newington, VA 22122",
      "phone": "703-533-2373",
      "image": "https://cdn.findpawpal.com/office/511975.jpg?f=webp&w=730"
    },
    {
      "slug": "dogs-deserve-better-of-the-new-river-valley-578855",
      "name": "Dogs Deserve Better of the New River Valley",
      "address": "528 Blue Grass Trail, Newport, VA 24128",
      "phone": "540-544-3058",
      "image": "https://cdn.findpawpal.com/office/578855.jpg?f=webp&w=730"
    },
    {
      "slug": "peninsula-spca-574951",
      "name": "Peninsula SPCA",
      "address": "523 J Clyde Morris Blvd, Newport News, VA 23601",
      "phone": "757-595-1399",
      "image": "https://cdn.findpawpal.com/office/574951.jpg?f=webp&w=730"
    },
    {
      "slug": "norfolk-animal-management-center-511474",
      "name": "Norfolk Animal Management Center",
      "address": "5585 Sabre Rd, Norfolk, VA 23502",
      "phone": "757-664-7387",
      "image": "https://cdn.findpawpal.com/office/511474.jpg?f=webp&w=730"
    },
    {
      "slug": "norfolk-spca-561335",
      "name": "Norfolk SPCA",
      "address": "916 Ballentine Blvd, Norfolk, VA 23504",
      "phone": "757-622-3319",
      "image": "https://cdn.findpawpal.com/office/561335.jpg?f=webp&w=730"
    },
    {
      "slug": "rainbow-animal-rescue-inc-511479",
      "name": "Rainbow Animal Rescue, Inc.",
      "address": "7701 Halprin Dr, Norfolk, VA 23518",
      "phone": "757-583-8777",
      "image": "https://cdn.findpawpal.com/office/511479.jpg?f=webp&w=730"
    },
    {
      "slug": "tazewell-county-animal-shelter-562034",
      "name": "Tazewell County Animal Shelter",
      "address": "3015 Lynn Hollow Road, North Tazewell, VA 24630",
      "phone": "276-988-5795",
      "image": "https://cdn.findpawpal.com/office/562034.jpg?f=webp&w=730"
    },
    {
      "slug": "eastern-shore-spca-646499",
      "name": "Eastern Shore SPCA",
      "address": "26528 Lankford Highway, Onancock, VA 23417",
      "phone": "757-787-7385",
      "image": "https://cdn.findpawpal.com/office/646499.jpg?f=webp&w=730"
    },
    {
      "slug": "onley-animal-shelter-683142",
      "name": "Onley Animal Shelter",
      "address": "26528 Lankford Highway, Onancock, VA 23417",
      "phone": "757-787-7385",
      "image": "https://cdn.findpawpal.com/office/683142.jpg?f=webp&w=730"
    },
    {
      "slug": "damiens-gift-feline-foundation-511482",
      "name": "Damien's Gift Feline Foundation",
      "address": "126 Landon Lane, Orange, VA 22960",
      "phone": "804-589-4592",
      "image": "https://cdn.findpawpal.com/office/511482.jpg?f=webp&w=730"
    },
    {
      "slug": "orange-county-humane-society-682992",
      "name": "Orange County Humane Society",
      "address": "PO Box 623, Orange, VA 22960",
      "phone": "540-672-0069",
      "image": "https://cdn.findpawpal.com/office/682992.jpg?f=webp&w=730"
    },
    {
      "slug": "rikkis-refuge-orange-574985",
      "name": "Rikki's Refuge Orange",
      "address": "PO Box 1357, Orange, VA 22960",
      "phone": "540-854-0870",
      "image": "https://cdn.findpawpal.com/office/574985.jpg?f=webp&w=730"
    },
    {
      "slug": "caring-for-creatures-foundation-706692",
      "name": "Caring for Creatures Foundation",
      "address": "352 Sanctuary Lane, Palmyra, VA 22963",
      "phone": "804-842-2404",
      "image": "https://cdn.findpawpal.com/office/706692.jpg?f=webp&w=730"
    },
    {
      "slug": "fluvanna-county-animal-control-578819",
      "name": "Fluvanna County Animal Control",
      "address": "PO Box 299, Palmyra, VA 22963",
      "phone": "",
      "image": "https://cdn.findpawpal.com/office/578819.jpg?f=webp&w=730"
    },
    {
      "slug": "giles-county-animal-rescue-inc-561123",
      "name": "Giles County Animal Rescue, Inc.",
      "address": "PO Box 354, Pearisburg, VA 24134",
      "phone": "540-921-2053",
      "image": "https://cdn.findpawpal.com/office/561123.jpg?f=webp&w=730"
    },
    {
      "slug": "giles-county-spca-511274",
      "name": "Giles County SPCA",
      "address": "240 Meadows Road, Pearisburg, VA 24134",
      "phone": "540-921-3512",
      "image": "https://cdn.findpawpal.com/office/511274.jpg?f=webp&w=730"
    },
    {
      "slug": "petersburg-animal-control-555121",
      "name": "Petersburg Animal Control",
      "address": "1600 Johnson Rd, Petersburg, VA 23805",
      "phone": "804-732-3654",
      "image": "https://cdn.findpawpal.com/office/555121.jpg?f=webp&w=730"
    },
    {
      "slug": "petersburg-animal-shelter-646749",
      "name": "Petersburg Animal Shelter",
      "address": "PO Box 2109, Petersburg, VA 23804",
      "phone": "804-732-4222",
      "image": "https://cdn.findpawpal.com/office/646749.jpg?f=webp&w=730"
    },
    {
      "slug": "spca-of-petersburg-561383",
      "name": "SPCA of Petersburg",
      "address": "PO Box 1174, Petersburg, VA 23804",
      "phone": "",
      "image": "https://cdn.findpawpal.com/office/561383.jpg?f=webp&w=730"
    },
    {
      "slug": "humane-society-of-caroline-county-644464",
      "name": "Humane Society of Caroline County",
      "address": "PO Box 173, Port Royal, VA 22535",
      "phone": "",
      "image": "https://cdn.findpawpal.com/office/644464.jpg?f=webp&w=730"
    },
    {
      "slug": "portsmouth-animal-control-511526",
      "name": "Portsmouth Animal Control",
      "address": "711 Crawford St, Portsmouth, VA 23704",
      "phone": "757-393-8430",
      "image": "https://cdn.findpawpal.com/office/511526.jpg?f=webp&w=730"
    },
    {
      "slug": "portsmouth-humane-society-554546",
      "name": "Portsmouth Humane Society",
      "address": "2704 Frederick Blvd, Portsmouth, VA 23704",
      "phone": "757-397-6004",
      "image": "https://cdn.findpawpal.com/office/554546.jpg?f=webp&w=730"
    },
    {
      "slug": "sosharpei-inc-646670",
      "name": "Sosharpei, Inc.",
      "address": "PO Box 452, Portsmouth, VA 23705",
      "phone": "757-687-7297",
      "image": "https://cdn.findpawpal.com/office/646670.jpg?f=webp&w=730"
    },
    {
      "slug": "tidewater-rabbit-rescue-554552",
      "name": "Tidewater Rabbit Rescue",
      "address": "PO Box 8015, Portsmouth, VA 23707",
      "phone": "",
      "image": "https://cdn.findpawpal.com/office/554552.jpg?f=webp&w=730"
    },
    {
      "slug": "second-chance-animal-shelter-644625",
      "name": "Second Chance Animal Shelter",
      "address": "PO Box 55, Powhatan, VA 23139",
      "phone": "804-598-2100",
      "image": "https://cdn.findpawpal.com/office/644625.jpg?f=webp&w=730"
    },
    {
      "slug": "charles-city-county-animal-shelter-555009",
      "name": "Charles City County Animal Shelter",
      "address": "11200 Carriage Road, Providence Forge, VA 23140",
      "phone": "804-829-9266",
      "image": "https://cdn.findpawpal.com/office/555009.jpg?f=webp&w=730"
    },
    {
      "slug": "new-kent-county-animal-control-644601",
      "name": "New Kent County Animal Control",
      "address": "6301 Olivet Church Road, Providence Forge, VA 23140",
      "phone": "804-966-9500",
      "image": "https://cdn.findpawpal.com/office/644601.jpg?f=webp&w=730"
    },
    {
      "slug": "pound-pals-of-radford-554594",
      "name": "Pound Pals of Radford",
      "address": "PO Box 2851, Radford, VA 24143",
      "phone": "703-633-2307",
      "image": "https://cdn.findpawpal.com/office/554594.jpg?f=webp&w=730"
    },
    {
      "slug": "radford-animal-control-646686",
      "name": "Radford Animal Control",
      "address": "104 Pulaski St, Radford, VA 24141",
      "phone": "703-731-3688",
      "image": "https://cdn.findpawpal.com/office/646686.jpg?f=webp&w=730"
    },
    {
      "slug": "reedville-animal-control-512065",
      "name": "Reedville Animal Control",
      "address": "75 Main Street, Reedville, VA 22539",
      "phone": "804-435-0822",
      "image": "https://cdn.findpawpal.com/office/512065.jpg?f=webp&w=730"
    },
    {
      "slug": "paws-and-claws-animal-rescue-706688",
      "name": "PAWS & Claws Animal Rescue",
      "address": "PO Box 2504, Reston, VA 20195",
      "phone": "703-689-0500",
      "image": "https://cdn.findpawpal.com/office/706688.jpg?f=webp&w=730"
    },
    {
      "slug": "reston-animal-shelter-555148",
      "name": "Reston Animal Shelter",
      "address": "1548 Northgate Square, Reston, VA 20190",
      "phone": "703-709-6186",
      "image": "https://cdn.findpawpal.com/office/555148.jpg?f=webp&w=730"
    },
    {
      "slug": "animal-adoption-and-rescue-foundation-529312",
      "name": "Animal Adoption and Rescue Foundation",
      "address": "PO Box 15262, Richmond, VA 23227",
      "phone": "804-254-0800",
      "image": "https://cdn.findpawpal.com/office/529312.jpg?f=webp&w=730"
    },
    {
      "slug": "greyhound-pets-of-america-554354",
      "name": "Greyhound Pets of America",
      "address": "PO Box 70811, Richmond, VA 23255",
      "phone": "804-527-3584",
      "image": "https://cdn.findpawpal.com/office/554354.jpg?f=webp&w=730"
    },
    {
      "slug": "henrico-county-animal-shelter-554914",
      "name": "Henrico County Animal Shelter",
      "address": "420 Dabbs House Road, Richmond, VA 23223",
      "phone": "804-652-3360",
      "image": "https://cdn.findpawpal.com/office/554914.jpg?f=webp&w=730"
    },
    {
      "slug": "henrico-humane-society-706778",
      "name": "Henrico Humane Society",
      "address": "10421 Woodman Rd, Richmond, VA 23228",
      "phone": "804-262-6634",
      "image": "https://cdn.findpawpal.com/office/706778.jpg?f=webp&w=730"
    },
    {
      "slug": "mid-atlantic-english-springer-spaniel-rescue-644734",
      "name": "Mid Atlantic English Springer Spaniel Rescue",
      "address": "PO Box 15354, Richmond, VA 23227",
      "phone": "301-362-0423",
      "image": "https://cdn.findpawpal.com/office/644734.jpg?f=webp&w=730"
    },
    {
      "slug": "richmond-animal-league-706679",
      "name": "Richmond Animal League",
      "address": "11401 International Drive, Richmond, VA 23236",
      "phone": "804-379-0046",
      "image": "https://cdn.findpawpal.com/office/706679.jpg?f=webp&w=730"
    },
    {
      "slug": "richmond-city-animal-shelter-706743",
      "name": "Richmond City Animal Shelter",
      "address": "1600 Chamberlayne Avenue, Richmond, VA 23222",
      "phone": "840-646-5573",
      "image": "https://cdn.findpawpal.com/office/706743.jpg?f=webp&w=730"
    },
    {
      "slug": "richmond-spca-575064",
      "name": "Richmond SPCA",
      "address": "2519 Hermitage Road, Richmond, VA 23220",
      "phone": "804-643-6785",
      "image": "https://cdn.findpawpal.com/office/575064.jpg?f=webp&w=730"
    },
    {
      "slug": "save-our-shelters-579199",
      "name": "Save Our Shelters",
      "address": "2933 West Cary Street, Richmond, VA 23221",
      "phone": "804-358-7499",
      "image": "https://cdn.findpawpal.com/office/579199.jpg?f=webp&w=730"
    },
    {
      "slug": "angels-of-assisi-561473",
      "name": "Angels of Assisi",
      "address": "415 Campbell Avenue Southwest, Roanoke, VA 24016",
      "phone": "540-344-8707",
      "image": "https://cdn.findpawpal.com/office/561473.jpg?f=webp&w=730"
    },
    {
      "slug": "roanoke-county-animal-control-512070",
      "name": "Roanoke County Animal Control",
      "address": "5925 Cove Road, Roanoke, VA 24019",
      "phone": "540-777-8606",
      "image": "https://cdn.findpawpal.com/office/512070.jpg?f=webp&w=730"
    },
    {
      "slug": "roanoke-county-animal-shelter-683068",
      "name": "Roanoke County Animal Shelter",
      "address": "PO Box 29800, Roanoke, VA 24018",
      "phone": "703-561-8040",
      "image": "https://cdn.findpawpal.com/office/683068.jpg?f=webp&w=730"
    },
    {
      "slug": "roanoke-valley-spca-706744",
      "name": "Roanoke Valley SPCA",
      "address": "1340 Baldwin Ave NE, Roanoke, VA 24012",
      "phone": "540-344-4840",
      "image": "https://cdn.findpawpal.com/office/706744.jpg?f=webp&w=730"
    },
    {
      "slug": "madison-county-animal-shelter-646867",
      "name": "Madison County Animal Shelter",
      "address": "4590 Shelby Road, Rochelle, VA 22738",
      "phone": "540-948-6945",
      "image": "https://cdn.findpawpal.com/office/646867.jpg?f=webp&w=730"
    },
    {
      "slug": "dream-catcher-farm-horse-sanctuary-528617",
      "name": "Dream Catcher Farm Horse Sanctuary",
      "address": "495 Adam Perry Road, Rocky Mount, VA 24151",
      "phone": "540-489-1262",
      "image": "https://cdn.findpawpal.com/office/528617.jpg?f=webp&w=730"
    },
    {
      "slug": "franklin-county-animal-control-578845",
      "name": "Franklin County Animal Control",
      "address": "9246 Virgil H Goode Highway, Rocky Mount, VA 24151",
      "phone": "540-483-7440",
      "image": "https://cdn.findpawpal.com/office/578845.jpg?f=webp&w=730"
    },
    {
      "slug": "franklin-county-humane-society-644522",
      "name": "Franklin County Humane Society",
      "address": "18401 Virgil H Goode Highway, Rocky Mount, VA 24151",
      "phone": "540-489-3491",
      "image": "https://cdn.findpawpal.com/office/644522.jpg?f=webp&w=730"
    },
    {
      "slug": "madison-greene-humane-society-579014",
      "name": "Madison-Greene Humane Society",
      "address": "375 Mays Road, Ruckersville, VA 22968",
      "phone": "434-985-3203",
      "image": "https://cdn.findpawpal.com/office/579014.jpg?f=webp&w=730"
    },
    {
      "slug": "tender-heart-rescue-706758",
      "name": "Tender Heart Rescue",
      "address": "7612 West Lee Highway, Rural Retreat, VA 24368",
      "phone": "276-620-2138",
      "image": "https://cdn.findpawpal.com/office/706758.jpg?f=webp&w=730"
    },
    {
      "slug": "campbell-county-animal-shelter-682876",
      "name": "Campbell County Animal Shelter",
      "address": "322 Dennis Riddle Drive, Rustburg, VA 24588",
      "phone": "",
      "image": "https://cdn.findpawpal.com/office/682876.jpg?f=webp&w=730"
    },
    {
      "slug": "humane-society-for-campbell-county-528449",
      "name": "Humane Society for Campbell County",
      "address": "PO Box 606, Rustburg, VA 24588",
      "phone": "804-821-4416",
      "image": "https://cdn.findpawpal.com/office/528449.jpg?f=webp&w=730"
    },
    {
      "slug": "salem-animal-shelter-555150",
      "name": "Salem Animal Shelter",
      "address": "1301 Indiana St, Salem, VA 24153",
      "phone": "540-375-3038",
      "image": "https://cdn.findpawpal.com/office/555150.jpg?f=webp&w=730"
    },
    {
      "slug": "middlesex-county-animal-shelter-646859",
      "name": "Middlesex County Animal Shelter",
      "address": "2840 General Puller Highway, Saluda, VA 23149",
      "phone": "804-758-5293",
      "image": "https://cdn.findpawpal.com/office/646859.jpg?f=webp&w=730"
    },
    {
      "slug": "laughing-horse-sanctuary-529349",
      "name": "Laughing Horse Sanctuary",
      "address": "8317 Grassland Drive, Sandy Level, VA 24161",
      "phone": "434-927-5298",
      "image": "https://cdn.findpawpal.com/office/529349.jpg?f=webp&w=730"
    },
    {
      "slug": "isle-of-wight-county-humane-society-561228",
      "name": "Isle of Wight County Humane Society",
      "address": "PO Box 273, Smithfield, VA 23431",
      "phone": "757-357-4214",
      "image": "https://cdn.findpawpal.com/office/561228.jpg?f=webp&w=730"
    },
    {
      "slug": "halifax-county-animal-control-529511",
      "name": "Halifax County Animal Control",
      "address": "1040 Farm Road, South Boston, VA 24592",
      "phone": "434-572-4292",
      "image": "https://cdn.findpawpal.com/office/529511.jpg?f=webp&w=730"
    },
    {
      "slug": "halifax-county-humane-society-644543",
      "name": "Halifax County Humane Society",
      "address": "PO Box 969, South Boston, VA 24592",
      "phone": "434-575-1473",
      "image": "https://cdn.findpawpal.com/office/644543.jpg?f=webp&w=730"
    },
    {
      "slug": "south-boston-animal-control-578898",
      "name": "South Boston Animal Control",
      "address": "640 Hamilton Boulevard, South Boston, VA 24592",
      "phone": "",
      "image": "https://cdn.findpawpal.com/office/578898.jpg?f=webp&w=730"
    },
    {
      "slug": "lionhearts-inc-529057",
      "name": "Lionhearts, Inc.",
      "address": "7509 Po River Drive, Spotsylvania, VA 22551",
      "phone": "540-582-6879",
      "image": "https://cdn.findpawpal.com/office/529057.jpg?f=webp&w=730"
    },
    {
      "slug": "travellers-rest-equine-elders-sanctuary-683026",
      "name": "Traveller's Rest Equine Elders Sanctuary",
      "address": "PO Box 2260, Spotsylvania, VA 22553",
      "phone": "540-972-0936",
      "image": "https://cdn.findpawpal.com/office/683026.jpg?f=webp&w=730"
    },
    {
      "slug": "virginia-greyhound-adoption-644655",
      "name": "Virginia Greyhound Adoption",
      "address": "PO Box 2059, Spotsylvania, VA 22553",
      "phone": "866-353-4649",
      "image": "https://cdn.findpawpal.com/office/644655.jpg?f=webp&w=730"
    },
    {
      "slug": "blm-wild-horse-and-burro-program-575386",
      "name": "BLM Wild Horse & Burro Program",
      "address": "7450 Boston Boulevard, Springfield, VA 22153",
      "phone": "800-370-3936",
      "image": "https://cdn.findpawpal.com/office/575386.jpg?f=webp&w=730"
    },
    {
      "slug": "pet-assistance-league-of-va-579239",
      "name": "Pet Assistance League of Va",
      "address": "PO Box 1076, Stafford, VA 22555",
      "phone": "540-659-5018",
      "image": "https://cdn.findpawpal.com/office/579239.jpg?f=webp&w=730"
    },
    {
      "slug": "stafford-county-animal-control-644715",
      "name": "Stafford County Animal Control",
      "address": "473 Eskimo Hill Road, Stafford, VA 22554",
      "phone": "540-658-7387",
      "image": "https://cdn.findpawpal.com/office/644715.jpg?f=webp&w=730"
    },
    {
      "slug": "stafford-spca-575270",
      "name": "Stafford SPCA",
      "address": "140 Andrew Chapel Road, Stafford, VA 22554",
      "phone": "540-657-7387",
      "image": "https://cdn.findpawpal.com/office/575270.jpg?f=webp&w=730"
    },
    {
      "slug": "the-dancing-bear-rescue-inc-511819",
      "name": "The Dancing Bear Rescue, Inc.",
      "address": "56 Buttercup Lane, Stafford, VA 22554",
      "phone": "540-288-1499",
      "image": "https://cdn.findpawpal.com/office/511819.jpg?f=webp&w=730"
    },
    {
      "slug": "wolfdog-rescue-resources-575274",
      "name": "Wolfdog Rescue Resources",
      "address": "5 Raines Court, Stafford, VA 22556",
      "phone": "540-720-8588",
      "image": "https://cdn.findpawpal.com/office/575274.jpg?f=webp&w=730"
    },
    {
      "slug": "greene-county-spca-579281",
      "name": "Greene County SPCA",
      "address": "PO Box 358, Stanardsville, VA 22973",
      "phone": "804-985-5210",
      "image": "https://cdn.findpawpal.com/office/579281.jpg?f=webp&w=730"
    },
    {
      "slug": "standardsville-animal-control-512024",
      "name": "Standardsville Animal Control",
      "address": "1005 Spotswood Trail, Stanardsville, VA 22973",
      "phone": "434-985-2222",
      "image": "https://cdn.findpawpal.com/office/512024.jpg?f=webp&w=730"
    },
    {
      "slug": "page-county-animal-shelter-644613",
      "name": "Page County Animal Shelter",
      "address": "1261 Goodrich Road, Stanley, VA 22851",
      "phone": "540-778-2101",
      "image": "https://cdn.findpawpal.com/office/644613.jpg?f=webp&w=730"
    },
    {
      "slug": "augusta-regional-spca-575108",
      "name": "Augusta Regional SPCA",
      "address": "33 Archery Lane, Staunton, VA 24401",
      "phone": "540-885-7722",
      "image": "https://cdn.findpawpal.com/office/575108.jpg?f=webp&w=730"
    },
    {
      "slug": "staunton-animal-control-511633",
      "name": "Staunton Animal Control",
      "address": "113 Olive Street, Staunton, VA 24401",
      "phone": "540-887-3337",
      "image": "https://cdn.findpawpal.com/office/511633.jpg?f=webp&w=730"
    },
    {
      "slug": "animal-shelter-578778",
      "name": "Animal Shelter",
      "address": "165 Sulgrave Court, Sterling, VA 20165",
      "phone": "757-456-1354",
      "image": "https://cdn.findpawpal.com/office/578778.jpg?f=webp&w=730"
    },
    {
      "slug": "dogwood-sheltie-rescue-706716",
      "name": "Dogwood Sheltie Rescue",
      "address": "12 Regis Circle, Sterling, VA 20164",
      "phone": "703-406-8920",
      "image": "https://cdn.findpawpal.com/office/706716.jpg?f=webp&w=730"
    },
    {
      "slug": "sussex-co-animal-shelter-561653",
      "name": "Sussex Co Animal Shelter",
      "address": "14493 Robinson Road, Stony Creek, VA 23882",
      "phone": "434-246-2167",
      "image": "https://cdn.findpawpal.com/office/561653.jpg?f=webp&w=730"
    },
    {
      "slug": "northern-virginia-sheltie-rescue-511923",
      "name": "Northern Virginia Sheltie Rescue",
      "address": "60 Penny Lane, Strasburg, VA 22657",
      "phone": "540-465-5936",
      "image": "https://cdn.findpawpal.com/office/511923.jpg?f=webp&w=730"
    },
    {
      "slug": "patrick-animal-welfare-society-682998",
      "name": "Patrick Animal Welfare Society",
      "address": "16 Doctor Kay Ln, Stuart, VA 24171",
      "phone": "703-694-3663",
      "image": "https://cdn.findpawpal.com/office/682998.jpg?f=webp&w=730"
    },
    {
      "slug": "patrick-county-animal-control-644615",
      "name": "Patrick County Animal Control",
      "address": "PO Box 466, Stuart, VA 24171",
      "phone": "276-694-6259",
      "image": "https://cdn.findpawpal.com/office/644615.jpg?f=webp&w=730"
    },
    {
      "slug": "spay-and-neuter-inc-579836",
      "name": "Spay and Neuter, Inc.",
      "address": "PO Box 769, Stuarts Draft, VA 24477",
      "phone": "540-480-7582",
      "image": "https://cdn.findpawpal.com/office/579836.jpg?f=webp&w=730"
    },
    {
      "slug": "chessie-rescue-va-683031",
      "name": "Chessie Rescue VA",
      "address": "PO Box 5304, Suffolk, VA 23435",
      "phone": "757-484-6507",
      "image": "https://cdn.findpawpal.com/office/683031.jpg?f=webp&w=730"
    },
    {
      "slug": "suffolk-animal-control-575472",
      "name": "Suffolk Animal Control",
      "address": "124 Forest Glen Dr, Suffolk, VA 23434",
      "phone": "757-514-7855",
      "image": "https://cdn.findpawpal.com/office/575472.jpg?f=webp&w=730"
    },
    {
      "slug": "tidewater-bichon-frise-rescue-561523",
      "name": "Tidewater Bichon Frise Rescue",
      "address": "PO Box 8084, Suffolk, VA 23438",
      "phone": "757-986-2275",
      "image": "https://cdn.findpawpal.com/office/561523.jpg?f=webp&w=730"
    },
    {
      "slug": "surry-county-spca-646710",
      "name": "Surry County SPCA",
      "address": "PO Box 96, Surry, VA 23883",
      "phone": "757-294-3077",
      "image": "https://cdn.findpawpal.com/office/646710.jpg?f=webp&w=730"
    },
    {
      "slug": "essex-county-animal-control-574677",
      "name": "Essex County Animal Control",
      "address": "PO Box 266, Tappahannock, VA 22560",
      "phone": "804-443-3346",
      "image": "https://cdn.findpawpal.com/office/574677.jpg?f=webp&w=730"
    },
    {
      "slug": "tazewell-county-animal-shelter-512030",
      "name": "Tazewell County Animal Shelter",
      "address": "108 East Main Street, Tazewell, VA 24651",
      "phone": "276-988-5795",
      "image": "https://cdn.findpawpal.com/office/512030.jpg?f=webp&w=730"
    },
    {
      "slug": "tazewell-county-humane-society-646798",
      "name": "Tazewell County Humane Society",
      "address": "PO Box 281, Tazewell, VA 24651",
      "phone": "540-988-4877",
      "image": "https://cdn.findpawpal.com/office/646798.jpg?f=webp&w=730"
    },
    {
      "slug": "madison-county-animal-control-561952",
      "name": "Madison County Animal Control",
      "address": "107 Church Street, Timberville, VA 22853",
      "phone": "540-948-5161",
      "image": "https://cdn.findpawpal.com/office/561952.jpg?f=webp&w=730"
    },
    {
      "slug": "pet-assistance-league-554580",
      "name": "Pet Assistance League",
      "address": "3498 Scelzi Court, Triangle, VA 22172",
      "phone": "703-221-8937",
      "image": "https://cdn.findpawpal.com/office/554580.jpg?f=webp&w=730"
    },
    {
      "slug": "animal-connections-inc-574717",
      "name": "Animal Connections, Inc.",
      "address": "2471 Troy Road, Troy, VA 22974",
      "phone": "434-589-1900",
      "image": "https://cdn.findpawpal.com/office/574717.jpg?f=webp&w=730"
    },
    {
      "slug": "fluvanna-spca-554214",
      "name": "Fluvanna SPCA",
      "address": "5239 Union Mills Road, Troy, VA 22974",
      "phone": "804-591-0123",
      "image": "https://cdn.findpawpal.com/office/554214.jpg?f=webp&w=730"
    },
    {
      "slug": "full-moon-rescue-561367",
      "name": "Full Moon Rescue",
      "address": "13246 Dowdy Lane, Unionville, VA 22567",
      "phone": "540-854-5780",
      "image": "https://cdn.findpawpal.com/office/561367.jpg?f=webp&w=730"
    },
    {
      "slug": "augusta-county-animal-control-644853",
      "name": "Augusta County Animal Control",
      "address": "PO Box 590, Verona, VA 24482",
      "phone": "540-245-5635",
      "image": "https://cdn.findpawpal.com/office/644853.jpg?f=webp&w=730"
    },
    {
      "slug": "lunenburg-county-animal-shelter-555107",
      "name": "Lunenburg County Animal Shelter",
      "address": "1320 Old Mansion Rd, Victoria, VA 23974",
      "phone": "434-696-5529",
      "image": "https://cdn.findpawpal.com/office/555107.jpg?f=webp&w=730"
    },
    {
      "slug": "vienna-animal-control-706805",
      "name": "Vienna Animal Control",
      "address": "215 Center Street South, Vienna, VA 22180",
      "phone": "703-255-6377",
      "image": "https://cdn.findpawpal.com/office/706805.jpg?f=webp&w=730"
    },
    {
      "slug": "vinton-animal-control-706791",
      "name": "Vinton Animal Control",
      "address": "311 South Pollard Street, Vinton, VA 24179",
      "phone": "540-983-0617",
      "image": "https://cdn.findpawpal.com/office/706791.jpg?f=webp&w=730"
    },
    {
      "slug": "ferret-haven-683037",
      "name": "Ferret Haven",
      "address": "2312 Starfish Rd, Virginia Beach, VA 23451",
      "phone": "757-481-3954",
      "image": "https://cdn.findpawpal.com/office/683037.jpg?f=webp&w=730"
    },
    {
      "slug": "k-9-new-life-center-646715",
      "name": "K-9 New Life Center",
      "address": "PO Box 6427, Virginia Beach, VA 23456",
      "phone": "757-721-2275",
      "image": "https://cdn.findpawpal.com/office/646715.jpg?f=webp&w=730"
    },
    {
      "slug": "tidewater-humane-society-646797",
      "name": "Tidewater Humane Society",
      "address": "PO Box 68489, Virginia Beach, VA 23471",
      "phone": "757-497-7729",
      "image": "https://cdn.findpawpal.com/office/646797.jpg?f=webp&w=730"
    },
    {
      "slug": "virginia-beach-animal-control-554682",
      "name": "Virginia Beach Animal Control",
      "address": "2665 Leroy Rd, Virginia Beach, VA 23456",
      "phone": "757-427-4158",
      "image": "https://cdn.findpawpal.com/office/554682.jpg?f=webp&w=730"
    },
    {
      "slug": "virginia-beach-spca-579275",
      "name": "Virginia Beach SPCA",
      "address": "3040 Holland Rd, Virginia Beach, VA 23453",
      "phone": "757-427-0070",
      "image": "https://cdn.findpawpal.com/office/579275.jpg?f=webp&w=730"
    },
    {
      "slug": "fauquier-county-animal-control-554482",
      "name": "Fauquier County Animal Control",
      "address": "78 West Lee Street, Warrenton, VA 20186",
      "phone": "540-347-6862",
      "image": "https://cdn.findpawpal.com/office/554482.jpg?f=webp&w=730"
    },
    {
      "slug": "richmond-animal-shelter-561465",
      "name": "Richmond Animal Shelter",
      "address": "PO Box 1000, Warsaw, VA 22572",
      "phone": "804-780-5397",
      "image": "https://cdn.findpawpal.com/office/561465.jpg?f=webp&w=730"
    },
    {
      "slug": "kitkat-rescue-579003",
      "name": "Kitkat Rescue",
      "address": "38581 Daymont Lane, Waterford, VA 20197",
      "phone": "540-882-9689",
      "image": "https://cdn.findpawpal.com/office/579003.jpg?f=webp&w=730"
    },
    {
      "slug": "loudoun-county-animal-shelter-644801",
      "name": "Loudoun County Animal Shelter",
      "address": "39820 Charles Town Pike, Waterford, VA 20197",
      "phone": "540-882-3211",
      "image": "https://cdn.findpawpal.com/office/644801.jpg?f=webp&w=730"
    },
    {
      "slug": "waynesboro-animal-control-575499",
      "name": "Waynesboro Animal Control",
      "address": "250 S Wayne Ave, Waynesboro, VA 22980",
      "phone": "540-942-6675",
      "image": "https://cdn.findpawpal.com/office/575499.jpg?f=webp&w=730"
    },
    {
      "slug": "king-and-queen-co-animal-control-706714",
      "name": "King & Queen Co Animal Control",
      "address": "PO Box 565, West Point, VA 23181",
      "phone": "",
      "image": "https://cdn.findpawpal.com/office/706714.jpg?f=webp&w=730"
    },
    {
      "slug": "heritage-humane-society-561569",
      "name": "Heritage Humane Society",
      "address": "430 Waller Mill Road, Williamsburg, VA 23185",
      "phone": "757-221-0150",
      "image": "https://cdn.findpawpal.com/office/561569.jpg?f=webp&w=730"
    },
    {
      "slug": "james-city-county-animal-control-shelter-511681",
      "name": "James City County Animal Control Shelter",
      "address": "PO Box 8784, Williamsburg, VA 23187",
      "phone": "757-253-1800",
      "image": "https://cdn.findpawpal.com/office/511681.jpg?f=webp&w=730"
    },
    {
      "slug": "frederick-county-animal-control-575151",
      "name": "Frederick County Animal Control",
      "address": "107 North Kent Street, Winchester, VA 22601",
      "phone": "540-665-5669",
      "image": "https://cdn.findpawpal.com/office/575151.jpg?f=webp&w=730"
    },
    {
      "slug": "frederick-county-animal-control-683132",
      "name": "Frederick County Animal Control",
      "address": "1080 Coverstone Drive, Winchester, VA 22602",
      "phone": "540-662-6162",
      "image": "https://cdn.findpawpal.com/office/683132.jpg?f=webp&w=730"
    },
    {
      "slug": "frederick-county-esther-boyd-animal-shelter-706697",
      "name": "Frederick County Esther Boyd Animal Shelter",
      "address": "161 Fort Collier Road, Winchester, VA 22603",
      "phone": "540-667-9192",
      "image": "https://cdn.findpawpal.com/office/706697.jpg?f=webp&w=730"
    },
    {
      "slug": "spca-winchester-646727",
      "name": "SPCA Winchester",
      "address": "115 Featherbed Lane, Winchester, VA 22601",
      "phone": "540-662-8616",
      "image": "https://cdn.findpawpal.com/office/646727.jpg?f=webp&w=730"
    },
    {
      "slug": "isle-of-wight-county-animal-control-574870",
      "name": "Isle of Wight County Animal Control",
      "address": "13100 Poor House Road, Windsor, VA 23487",
      "phone": "757-365-6318",
      "image": "https://cdn.findpawpal.com/office/574870.jpg?f=webp&w=730"
    },
    {
      "slug": "wise-county-animal-control-579313",
      "name": "Wise County Animal Control",
      "address": "PO Box 570, Wise, VA 24293",
      "phone": "276-679-6750",
      "image": "https://cdn.findpawpal.com/office/579313.jpg?f=webp&w=730"
    },
    {
      "slug": "dachshund-rescue-of-north-america-561614",
      "name": "Dachshund Rescue of North America",
      "address": "12497 Lolly Post Lane, Woodbridge, VA 22192",
      "phone": "703-491-3894",
      "image": "https://cdn.findpawpal.com/office/561614.jpg?f=webp&w=730"
    },
    {
      "slug": "greyhound-pets-of-america-northern-virginia-575185",
      "name": "Greyhound Pets of America - Northern Virginia",
      "address": "PO Box 6037, Woodbridge, VA 22195",
      "phone": "800-366-1472",
      "image": "https://cdn.findpawpal.com/office/575185.jpg?f=webp&w=730"
    },
    {
      "slug": "liberty-golden-retriever-rescue-528993",
      "name": "Liberty Golden Retriever Rescue",
      "address": "PO Box 5365, Woodbridge, VA 22194",
      "phone": "",
      "image": "https://cdn.findpawpal.com/office/528993.jpg?f=webp&w=730"
    },
    {
      "slug": "noahs-ark-foundation-683053",
      "name": "Noah's Ark Foundation",
      "address": "PO Box 7862, Woodbridge, VA 22195",
      "phone": "703-831-4153",
      "image": "https://cdn.findpawpal.com/office/683053.jpg?f=webp&w=730"
    },
    {
      "slug": "potomac-animal-allies-644626",
      "name": "Potomac Animal Allies",
      "address": "PO Box 207, Woodbridge, VA 22194",
      "phone": "703-791-2900",
      "image": "https://cdn.findpawpal.com/office/644626.jpg?f=webp&w=730"
    },
    {
      "slug": "spca-of-prince-william-county-575031",
      "name": "SPCA of Prince William County",
      "address": "PO Box 6631, Woodbridge, VA 22195",
      "phone": "571-222-0033",
      "image": "https://cdn.findpawpal.com/office/575031.jpg?f=webp&w=730"
    },
    {
      "slug": "humane-society-of-shenandoah-county-706788",
      "name": "Humane Society of Shenandoah County",
      "address": "PO Box 173, Woodstock, VA 22664",
      "phone": "703-984-8431",
      "image": "https://cdn.findpawpal.com/office/706788.jpg?f=webp&w=730"
    },
    {
      "slug": "wythe-county-humane-706759",
      "name": "Wythe County Humane",
      "address": "245 South 4th Street, Wytheville, VA 24382",
      "phone": "703-228-7683",
      "image": "https://cdn.findpawpal.com/office/706759.jpg?f=webp&w=730"
    },
    {
      "slug": "wytheville-animal-control-529157",
      "name": "Wytheville Animal Control",
      "address": "185 West Spring Street, Wytheville, VA 24382",
      "phone": "276-223-3397",
      "image": "https://cdn.findpawpal.com/office/529157.jpg?f=webp&w=730"
    },
    {
      "slug": "southeastern-virginia-golden-retriever-rescue-education-and-training-inc-529163",
      "name": "Southeastern Virginia Golden Retriever Rescue, Education, and Training, Inc.",
      "address": "PO Box 8014, Yorktown, VA 23693",
      "phone": "757-827-8561",
      "image": "https://cdn.findpawpal.com/office/529163.jpg?f=webp&w=730"
    },
    {
      "slug": "york-county-voter-registrar-554961",
      "name": "York County Voter Registrar",
      "address": "224 Ballard Street, Yorktown, VA 23690",
      "phone": "757-890-3440",
      "image": "https://cdn.findpawpal.com/office/554961.jpg?f=webp&w=730"
    }
  ]
}