{
  "fetchedAt": "2026-06-27T20:13:44.044126+00:00",
  "state": {
    "slug": "virginia",
    "name": "Virginia"
  },
  "city": {
    "slug": "dunn-loring",
    "name": "Dunn Loring",
    "label": "Dunn Loring, VA"
  },
  "source": "https://www.findpawpal.com/animal-shelter/virginia/dunn-loring/",
  "offices": [
    {
      "officeId": 579610,
      "slug": "westie-rescue-of-the-mid-atlantic-states-inc-579610",
      "name": "Westie Rescue of the Mid-Atlantic States, Inc.",
      "address": "PO Box 342, Dunn Loring, VA 22027",
      "phone": "703-671-1039",
      "image": "./img/shelter/office/579610.webp",
      "url": "https://www.findpawpal.com/animal-shelter/westie-rescue-of-the-mid-atlantic-states-inc-579610/",
      "imageUrl": "https://cdn.findpawpal.com/office/579610.jpg?f=webp&w=730"
    }
  ]
}