{
  "fetchedAt": "2026-06-27T19:16:53.578401+00:00",
  "state": {
    "slug": "mississippi",
    "name": "Mississippi"
  },
  "city": {
    "slug": "olive-branch",
    "name": "Olive Branch",
    "label": "Olive Branch, MS"
  },
  "source": "https://www.findpawpal.com/animal-shelter/mississippi/olive-branch/",
  "offices": [
    {
      "officeId": 113569,
      "slug": "olive-branch-animal-control-113569",
      "name": "Olive Branch Animal Control",
      "address": "7100 STATELINE Rd, Olive Branch, MS 38654",
      "phone": "662-895-4582",
      "image": "./img/shelter/office/113569.webp",
      "url": "https://www.findpawpal.com/animal-shelter/olive-branch-animal-control-113569/",
      "imageUrl": "https://cdn.findpawpal.com/office/113569.jpg?f=webp&w=730"
    }
  ]
}